<?xml version="1.0" encoding="UTF-8"?>
<!DOCTYPE DjVuXML PUBLIC "-//W3C//DTD DjVuXML 1.1//EN" "pubtext/DjVuXML-s.dtd">
<DjVuXML>
<HEAD>file://localhost/home/sriranga/Desktop/suresh/ntg/Volumes/050-052/0052.djvu</HEAD>
<BODY>
<OBJECT data="file://localhost/home/sriranga/Desktop/suresh/ntg/Volumes/050-052/0052.djvu" type="image/x.djvu" height="4709" width="3365" usemap="0052.djvu" >
<PARAM name="DPI" value="400" />
<PARAM name="GAMMA" value="2.200000" />
    <HIDDENTEXT>
      <PAGECOLUMN>
        <REGION>
          <PARAGRAPH>
            <LINE>
              <WORD coords="386,521,567,426">भूमिका</WORD>
              <WORD coords="591,502,711,454">बदल</WORD>
              <WORD coords="735,501,835,427">गयी</WORD>
              <WORD coords="860,499,922,426">तो</WORD>
              <WORD coords="949,506,1063,452">इष्ट&apos;</WORD>
              <WORD coords="1088,498,1157,424">को</WORD>
              <WORD coords="1183,497,1301,448">खास</WORD>
              <WORD coords="1324,508,1435,444">तरह</WORD>
              <WORD coords="1460,494,1530,438">का</WORD>
              <WORD coords="1556,494,1827,417">राजनीतिक</WORD>
              <WORD coords="1856,490,1931,426">रंग</WORD>
              <WORD coords="1956,488,2076,415">दिया</WORD>
              <WORD coords="2102,489,2211,409">जानै</WORD>
              <WORD coords="2239,487,2346,440">लगा</WORD>
              <WORD coords="2376,484,2388,438">।</WORD>
              <WORD coords="2435,504,2528,439">कुछ</WORD>
              <WORD coords="2553,484,2661,412">लोग</WORD>
              <WORD coords="2691,486,2806,412">जेलों</WORD>
              <WORD coords="2831,484,2874,420">में</WORD>
              <WORD coords="2901,486,2969,413">भी</WORD>
            </LINE>
            <LINE>
              <WORD coords="387,597,480,536">चले</WORD>
              <WORD coords="505,598,583,535">गये</WORD>
              <WORD coords="614,597,625,552">।</WORD>
              <WORD coords="658,603,776,534">इससे</WORD>
              <WORD coords="803,594,868,532">भी</WORD>
              <WORD coords="896,595,1128,530">आन्दोलन</WORD>
              <WORD coords="1156,591,1224,530">को</WORD>
              <WORD coords="1250,592,1361,529">क्षति</WORD>
              <WORD coords="1386,608,1528,524">पहुँची</WORD>
              <WORD coords="1558,588,1569,540">।</WORD>
              <WORD coords="1629,598,1859,524">निस्सन्देह</WORD>
              <WORD coords="1884,597,1959,538">यह</WORD>
              <WORD coords="1984,583,2211,519">वामपन्धी</WORD>
              <WORD coords="2239,582,2371,519">मोर्चा</WORD>
              <WORD coords="2399,591,2476,533">था,</WORD>
              <WORD coords="2505,597,2637,517">किन्तु</WORD>
              <WORD coords="2664,586,2788,516">इसमें</WORD>
              <WORD coords="2813,582,2970,533">उदार-</WORD>
            </LINE>
            <LINE>
              <WORD coords="386,704,520,632">वादी,</WORD>
              <WORD coords="546,695,752,630">वामपंथी</WORD>
              <WORD coords="778,693,881,628">और</WORD>
              <WORD coords="906,692,1059,627">कांग्रेस</WORD>
              <WORD coords="1112,688,1155,627">में</WORD>
              <WORD coords="1181,688,1291,643">काम</WORD>
              <WORD coords="1318,689,1549,622">करनेवाले</WORD>
              <WORD coords="1575,685,1643,623">भी</WORD>
              <WORD coords="1694,700,1999,621">हिल-जुलकर</WORD>
              <WORD coords="2038,681,2148,633">काम</WORD>
              <WORD coords="2172,680,2293,617">करते</WORD>
              <WORD coords="2322,676,2365,617">थे</WORD>
              <WORD coords="2398,678,2409,631">।</WORD>
              <WORD coords="2467,692,2543,631">यह</WORD>
              <WORD coords="2571,677,2741,632">व्यापक</WORD>
              <WORD coords="2766,679,2871,630">स्तर</WORD>
              <WORD coords="2898,678,2970,633">पर</WORD>
            </LINE>
            <LINE>
              <WORD coords="385,794,612,728">आधारित</WORD>
              <WORD coords="637,790,938,726">जनतंत्रात्मक</WORD>
              <WORD coords="964,788,1211,718">मंडलीय</WORD>
              <WORD coords="1242,786,1253,742">।</WORD>
            </LINE>
          </PARAGRAPH>
        </REGION>
      </PAGECOLUMN>
      <PAGECOLUMN>
        <REGION>
          <PARAGRAPH>
            <LINE>
              <WORD coords="597,973,672,921">इन</WORD>
              <WORD coords="698,967,754,903">दो</WORD>
              <WORD coords="782,982,891,919">तरह</WORD>
              <WORD coords="917,966,963,903">के</WORD>
              <WORD coords="990,966,1161,902">रंगमंच</WORD>
              <WORD coords="1194,963,1261,899">को</WORD>
              <WORD coords="1287,964,1415,899">देखने</WORD>
              <WORD coords="1434,983,1481,898">है</WORD>
              <WORD coords="1502,961,1598,913">बाद</WORD>
              <WORD coords="1625,963,1817,898">आजादी</WORD>
              <WORD coords="1841,961,1888,896">के</WORD>
              <WORD coords="1922,959,2019,909">बाद</WORD>
              <WORD coords="2046,955,2113,908">का</WORD>
              <WORD coords="2141,954,2310,890">रंगमंच</WORD>
              <WORD coords="2359,953,2468,885">कैसा</WORD>
              <WORD coords="2501,953,2650,906">लगता</WORD>
              <WORD coords="2702,969,2740,889">है</WORD>
              <WORD coords="2769,947,2797,887">है</WORD>
              <WORD coords="2868,952,2974,889">किन</WORD>
            </LINE>
            <LINE>
              <WORD coords="391,1069,501,1001">अ&apos;र्थों</WORD>
              <WORD coords="520,1066,562,1002">में</WORD>
              <WORD coords="581,1082,658,1020">यह</WORD>
              <WORD coords="683,1065,806,1004">उनसे</WORD>
              <WORD coords="832,1065,966,1016">अलग</WORD>
              <WORD coords="992,1075,1049,998">हो</WORD>
              <WORD coords="1075,1063,1204,1017">जाता</WORD>
              <WORD coords="1229,1078,1268,998">हैं</WORD>
              <WORD coords="1292,1060,1317,999">१</WORD>
            </LINE>
          </PARAGRAPH>
        </REGION>
      </PAGECOLUMN>
      <PAGECOLUMN>
        <REGION>
          <PARAGRAPH>
            <LINE>
              <WORD coords="598,1256,683,1200">एक</WORD>
              <WORD coords="714,1246,774,1184">तो</WORD>
              <WORD coords="800,1264,896,1176">मुझे</WORD>
              <WORD coords="922,1246,1037,1198">आज</WORD>
              <WORD coords="1062,1242,1109,1182">के</WORD>
              <WORD coords="1134,1255,1307,1182">थिएटर</WORD>
              <WORD coords="1333,1243,1377,1181">में</WORD>
              <WORD coords="1402,1242,1635,1178">आन्दोलन</WORD>
              <WORD coords="1661,1252,1729,1197">का</WORD>
              <WORD coords="1754,1242,1830,1180">रेंग</WORD>
              <WORD coords="1854,1242,1978,1194">नजर</WORD>
              <WORD coords="2002,1251,2101,1176">नहीं</WORD>
              <WORD coords="2124,1236,2254,1188">आता</WORD>
              <WORD coords="2277,1234,2288,1189">।</WORD>
              <WORD coords="2322,1248,2441,1172">पहले</WORD>
              <WORD coords="2466,1247,2640,1172">थिएटर</WORD>
              <WORD coords="2667,1235,2709,1172">में</WORD>
              <WORD coords="2736,1245,2822,1189">एक</WORD>
              <WORD coords="2839,1251,2981,1190">लहर-</WORD>
            </LINE>
            <LINE>
              <WORD coords="391,1341,456,1279">सी</WORD>
              <WORD coords="482,1341,580,1278">उठी</WORD>
              <WORD coords="606,1347,686,1277">थी,</WORD>
              <WORD coords="714,1341,805,1278">भले</WORD>
              <WORD coords="830,1353,889,1277">ही</WORD>
              <WORD coords="908,1338,1034,1276">सचेत</WORD>
              <WORD coords="1059,1339,1179,1275">करने</WORD>
              <WORD coords="1223,1337,1290,1274">को</WORD>
              <WORD coords="1316,1336,1415,1273">उठी</WORD>
              <WORD coords="1441,1350,1516,1273">हो,</WORD>
              <WORD coords="1542,1337,1662,1272">अपने</WORD>
              <WORD coords="1689,1349,1795,1290">साथ</WORD>
              <WORD coords="1822,1334,1870,1272">ले</WORD>
              <WORD coords="1884,1295,1889,1291">३</WORD>
              <WORD coords="1912,1336,2045,1271">चलने</WORD>
              <WORD coords="2070,1332,2140,1270">को</WORD>
              <WORD coords="2167,1332,2268,1270">उठी</WORD>
              <WORD coords="2293,1346,2354,1268">हो</WORD>
              <WORD coords="2383,1333,2531,1285">अथवा</WORD>
              <WORD coords="2556,1334,2764,1270">प्रभावित</WORD>
              <WORD coords="2791,1334,2980,1269">करनेके</WORD>
            </LINE>
            <LINE>
              <WORD coords="391,1450,499,1373">लिए</WORD>
              <WORD coords="517,1437,616,1374">उठी</WORD>
              <WORD coords="641,1449,698,1372">हो</WORD>
              <WORD coords="729,1436,740,1391">।</WORD>
              <WORD coords="784,1453,914,1372">किन्तु</WORD>
              <WORD coords="938,1445,1024,1388">एक</WORD>
              <WORD coords="1049,1447,1252,1371">लहर-सी</WORD>
              <WORD coords="1278,1435,1340,1373">थी</WORD>
              <WORD coords="1366,1434,1434,1370">जो</WORD>
              <WORD coords="1452,1432,1536,1386">अब</WORD>
              <WORD coords="1560,1448,1723,1360">नहों३है</WORD>
              <WORD coords="1755,1437,1766,1390">।</WORD>
              <WORD coords="1796,1432,2042,1368">कभी-कभी</WORD>
              <WORD coords="2066,1430,2213,1375">उगता</WORD>
              <WORD coords="2233,1444,2269,1365">है</WORD>
              <WORD coords="2296,1429,2365,1365">कि</WORD>
              <WORD coords="2391,1444,2512,1367">पुष्टि</WORD>
              <WORD coords="2537,1442,2710,1365">र्थिएदर</WORD>
              <WORD coords="2736,1432,2840,1365">जोर</WORD>
              <WORD coords="2858,1443,2979,1385">पकड़</WORD>
            </LINE>
            <LINE>
              <WORD coords="391,1545,485,1485">रहा</WORD>
              <WORD coords="509,1546,545,1469">है</WORD>
              <WORD coords="577,1535,589,1490">1</WORD>
              <WORD coords="620,1539,734,1486">इच्छा</WORD>
              <WORD coords="748,1545,903,1469">बिहार</WORD>
              <WORD coords="931,1532,1036,1468">और</WORD>
              <WORD coords="1060,1530,1171,1484">मध्य</WORD>
              <WORD coords="1198,1530,1318,1466">प्रदेश</WORD>
              <WORD coords="1345,1529,1494,1466">सक्रिय</WORD>
              <WORD coords="1522,1545,1557,1464">है</WORD>
              <WORD coords="1593,1531,1604,1486">।</WORD>
              <WORD coords="1623,1547,1885,1465">थोड़ा-बहुत</WORD>
              <WORD coords="1912,1533,2055,1463">बम्बई</WORD>
              <WORD coords="2083,1525,2126,1464">में</WORD>
              <WORD coords="2149,1527,2161,1481">।</WORD>
              <WORD coords="2192,1527,2354,1462">दि-तली</WORD>
              <WORD coords="2372,1525,2414,1462">में</WORD>
              <WORD coords="2433,1527,2494,1463">तो</WORD>
              <WORD coords="2510,1541,2608,1464">नहीं</WORD>
              <WORD coords="2623,1524,2671,1462">के</WORD>
              <WORD coords="2695,1527,2868,1481">बराबर</WORD>
              <WORD coords="2893,1543,2932,1465">है</WORD>
              <WORD coords="2962,1532,2976,1483">है</WORD>
            </LINE>
            <LINE>
              <WORD coords="395,1646,493,1566">इसी</WORD>
              <WORD coords="518,1627,648,1566">भाँति</WORD>
              <WORD coords="673,1629,758,1583">जन</WORD>
              <WORD coords="777,1647,915,1581">नाट्य</WORD>
              <WORD coords="942,1627,1032,1567">मंच</WORD>
              <WORD coords="1060,1636,1162,1581">बडा</WORD>
              <WORD coords="1188,1627,1339,1562">सक्रिय</WORD>
              <WORD coords="1367,1641,1403,1563">है</WORD>
              <WORD coords="1433,1626,1445,1580">।</WORD>
              <WORD coords="1478,1625,1590,1579">आज</WORD>
              <WORD coords="1617,1637,1704,1579">एक</WORD>
              <WORD coords="1715,1644,1833,1562">ड्डऔर</WORD>
              <WORD coords="1861,1640,1972,1580">तरह</WORD>
              <WORD coords="2000,1624,2067,1579">का</WORD>
              <WORD coords="2093,1624,2220,1561">संकट</WORD>
              <WORD coords="2248,1637,2285,1559">है</WORD>
              <WORD coords="2318,1626,2329,1579">।</WORD>
              <WORD coords="2361,1623,2718,1560">साम्प्रदायिकता</WORD>
              <WORD coords="2743,1625,2813,1578">का</WORD>
              <WORD coords="2839,1632,2979,1562">संकट,</WORD>
            </LINE>
            <LINE>
              <WORD coords="393,1727,546,1664">आतंक</WORD>
              <WORD coords="572,1726,641,1680">का</WORD>
              <WORD coords="666,1726,789,1662">संकट</WORD>
              <WORD coords="842,1724,946,1662">और</WORD>
              <WORD coords="1002,1723,1243,1674">भ्रष्टाचार</WORD>
              <WORD coords="1251,1723,1339,1660">बका</WORD>
              <WORD coords="1364,1722,1488,1662">संकट</WORD>
              <WORD coords="1518,1724,1531,1678">1</WORD>
              <WORD coords="1591,1722,1659,1657">जो</WORD>
              <WORD coords="1688,1736,1857,1659">रंगमंच</WORD>
              <WORD coords="1904,1723,1952,1660">के</WORD>
              <WORD coords="1978,1721,2084,1674">साथ</WORD>
              <WORD coords="2140,1737,2227,1651">जुडे</WORD>
              <WORD coords="2278,1734,2391,1659">रहते</WORD>
              <WORD coords="2430,1734,2467,1654">है</WORD>
              <WORD coords="2494,1721,2611,1657">और</WORD>
              <WORD coords="2656,1720,2761,1674">साथ</WORD>
              <WORD coords="2791,1735,2850,1658">ही</WORD>
              <WORD coords="2877,1721,2982,1676">साथ</WORD>
            </LINE>
            <LINE>
              <WORD coords="392,1821,588,1773">व्यवस्था</WORD>
              <WORD coords="613,1819,661,1757">के</WORD>
              <WORD coords="687,1820,790,1774">साथ</WORD>
              <WORD coords="830,1833,930,1758">नहीं</WORD>
              <WORD coords="957,1836,1043,1751">जुडे</WORD>
              <WORD coords="1088,1834,1200,1755">होते,</WORD>
              <WORD coords="1228,1816,1270,1755">वे</WORD>
              <WORD coords="1321,1817,1441,1754">अपने</WORD>
              <WORD coords="1480,1818,1647,1755">सीमित</WORD>
              <WORD coords="1688,1818,1859,1753">साधनों</WORD>
              <WORD coords="1885,1816,1934,1753">के</WORD>
              <WORD coords="1960,1816,2127,1769">आधार</WORD>
              <WORD coords="2154,1815,2226,1767">पर</WORD>
              <WORD coords="2252,1814,2385,1750">लोगों</WORD>
              <WORD coords="2411,1816,2494,1769">तक</WORD>
              <WORD coords="2520,1835,2680,1751">पहुँचने</WORD>
              <WORD coords="2706,1818,2775,1754">की</WORD>
              <WORD coords="2800,1816,2984,1752">कोशिश</WORD>
            </LINE>
            <LINE>
              <WORD coords="393,1916,512,1852">करते</WORD>
              <WORD coords="540,1928,577,1853">है</WORD>
              <WORD coords="608,1918,620,1873">।</WORD>
              <WORD coords="650,1915,810,1868">सफदर</WORD>
              <WORD coords="837,1927,1004,1854">हाशमी</WORD>
              <WORD coords="1028,1913,1095,1869">का</WORD>
              <WORD coords="1136,1914,1244,1847">कार्य</WORD>
              <WORD coords="1267,1920,1366,1852">इसी</WORD>
              <WORD coords="1391,1912,1533,1866">प्रकार</WORD>
              <WORD coords="1559,1912,1627,1864">का</WORD>
              <WORD coords="1652,1925,1691,1850">है</WORD>
              <WORD coords="1722,1913,1734,1867">।</WORD>
              <WORD coords="1796,1912,1904,1848">जिन</WORD>
              <WORD coords="1959,1911,2088,1847">लोगों</WORD>
              <WORD coords="2137,1910,2179,1850">में</WORD>
              <WORD coords="2204,1927,2331,1864">लगन</WORD>
              <WORD coords="2359,1913,2422,1849">थी</WORD>
              <WORD coords="2466,1911,2507,1849">वे</WORD>
              <WORD coords="2534,1912,2678,1866">अपना</WORD>
              <WORD coords="2725,1912,2834,1865">काम</WORD>
              <WORD coords="2859,1913,2981,1845">करते</WORD>
            </LINE>
            <LINE>
              <WORD coords="395,2023,466,1949">रहे</WORD>
              <WORD coords="499,2014,511,1969">।</WORD>
              <WORD coords="555,2011,667,1966">आज</WORD>
              <WORD coords="706,2031,884,1946">बहुत-से</WORD>
              <WORD coords="913,2030,1265,1947">युवक-प्रतियाँ</WORD>
              <WORD coords="1291,2025,1367,1965">यह</WORD>
              <WORD coords="1412,2009,1629,1960">समझकर</WORD>
              <WORD coords="1656,2030,1725,1946">कि,</WORD>
              <WORD coords="1757,2023,1834,1963">यह</WORD>
              <WORD coords="1874,2020,1985,1963">वक्त</WORD>
              <WORD coords="2010,2022,2048,1943">है</WORD>
              <WORD coords="2073,2008,2142,1944">कि</WORD>
              <WORD coords="2167,2019,2247,1960">हम</WORD>
              <WORD coords="2292,2008,2462,1947">रंगमंच</WORD>
              <WORD coords="2487,2010,2536,1947">के</WORD>
              <WORD coords="2561,2010,2707,1945">जरिये</WORD>
              <WORD coords="2762,2011,2913,1964">समाज</WORD>
              <WORD coords="2939,2008,2984,1947">में</WORD>
            </LINE>
            <LINE>
              <WORD coords="391,2108,501,2060">काम</WORD>
              <WORD coords="527,2116,628,2044">करें:,</WORD>
              <WORD coords="655,2108,806,2044">सक्रिय</WORD>
              <WORD coords="832,2126,908,2062">हुए</WORD>
              <WORD coords="933,2121,971,2045">हैं</WORD>
              <WORD coords="1011,2108,1023,2062">।</WORD>
              <WORD coords="1072,2107,1143,2059">पर</WORD>
              <WORD coords="1167,2121,1241,2060">यह</WORD>
              <WORD coords="1281,2121,1424,2061">कहता</WORD>
              <WORD coords="1451,2106,1520,2042">किं</WORD>
              <WORD coords="1546,2105,1630,2057">अब</WORD>
              <WORD coords="1657,2125,1769,2039">वैसी</WORD>
              <WORD coords="1810,2118,1867,2041">ही</WORD>
              <WORD coords="1909,2118,2029,2057">लहर</WORD>
              <WORD coords="2065,2104,2180,2040">चली</WORD>
              <WORD coords="2200,2116,2237,2037">है</WORD>
              <WORD coords="2266,2104,2381,2036">जैसी</WORD>
              <WORD coords="2407,2107,2491,2059">उस</WORD>
              <WORD coords="2520,2107,2669,2041">जमाने</WORD>
              <WORD coords="2689,2105,2731,2043">में</WORD>
              <WORD coords="2760,2118,2985,2042">थी-----&quot;</WORD>
            </LINE>
            <LINE>
              <WORD coords="397,2216,541,2154">कहना</WORD>
              <WORD coords="567,2201,712,2138">कठिन</WORD>
              <WORD coords="739,2216,777,2139">है</WORD>
              <WORD coords="805,2203,824,2157">।&apos;</WORD>
            </LINE>
          </PARAGRAPH>
          <PARAGRAPH>
            <LINE>
              <WORD coords="603,2313,732,2233">दूसरे,</WORD>
              <WORD coords="757,2312,895,2231">हिन्दी</WORD>
              <WORD coords="920,2299,1087,2235">रंगमंच</WORD>
              <WORD coords="1113,2299,1184,2235">की</WORD>
              <WORD coords="1207,2300,1327,2251">तरफ</WORD>
              <WORD coords="1345,2299,1454,2236">लोग</WORD>
              <WORD coords="1474,2317,1631,2249">उन्मुख</WORD>
              <WORD coords="1658,2317,1748,2252">हुए;</WORD>
              <WORD coords="1765,2310,1801,2235">हैं</WORD>
              <WORD coords="1828,2296,1845,2249">है</WORD>
              <WORD coords="1877,2310,1994,2235">पहले</WORD>
              <WORD coords="2020,2298,2270,2235">कमीज-कभी</WORD>
              <WORD coords="2294,2300,2436,2252">नाटक</WORD>
              <WORD coords="2462,2299,2588,2234">देखने</WORD>
              <WORD coords="2610,2298,2678,2235">को</WORD>
              <WORD coords="2712,2299,2863,2233">मिलते</WORD>
              <WORD coords="2892,2299,2934,2235">थे</WORD>
              <WORD coords="2966,2298,2977,2252">।</WORD>
            </LINE>
            <LINE>
              <WORD coords="394,2393,460,2329">जो</WORD>
              <WORD coords="486,2396,628,2348">नाटक</WORD>
              <WORD coords="652,2398,767,2332">लिखे</WORD>
              <WORD coords="786,2406,898,2330">जातें</WORD>
              <WORD coords="920,2404,978,2331">थे,</WORD>
              <WORD coords="1007,2393,1045,2332">वे</WORD>
              <WORD coords="1074,2396,1238,2332">रंगमंच</WORD>
              <WORD coords="1265,2394,1312,2329">के</WORD>
              <WORD coords="1331,2404,1439,2330">लिए</WORD>
              <WORD coords="1465,2401,1577,2329">इतने</WORD>
              <WORD coords="1597,2418,1793,2347">उपयुक्त</WORD>
              <WORD coords="1818,2410,1916,2333">नहीं</WORD>
              <WORD coords="1943,2410,2038,2326">होते</WORD>
              <WORD coords="2059,2392,2101,2330">थे</WORD>
              <WORD coords="2132,2398,2144,2352">।</WORD>
              <WORD coords="2176,2394,2260,2347">अब</WORD>
              <WORD coords="2285,2396,2393,2330">फिर</WORD>
              <WORD coords="2417,2394,2460,2330">से</WORD>
              <WORD coords="2487,2396,2577,2332">मंच</WORD>
              <WORD coords="2605,2394,2673,2331">की</WORD>
              <WORD coords="2699,2396,2888,2331">जरूरतों</WORD>
              <WORD coords="2914,2394,2982,2328">को</WORD>
            </LINE>
            <LINE>
              <WORD coords="392,2490,519,2442">ध्यान</WORD>
              <WORD coords="537,2489,582,2428">में</WORD>
              <WORD coords="606,2492,772,2445">रखकर</WORD>
              <WORD coords="799,2492,956,2429">अधिक</WORD>
              <WORD coords="980,2492,1122,2444">नाटक</WORD>
              <WORD coords="1146,2493,1262,2428">लिखे</WORD>
              <WORD coords="1286,2490,1391,2428">जाते</WORD>
              <WORD coords="1428,2503,1465,2427">है</WORD>
              <WORD coords="1494,2489,1505,2444">।</WORD>
              <WORD coords="1537,2491,1692,2429">(संख्या</WORD>
              <WORD coords="1719,2493,1789,2429">की</WORD>
              <WORD coords="1816,2511,1935,2429">दृष्टि</WORD>
              <WORD coords="1954,2491,1998,2428">से</WORD>
              <WORD coords="2024,2492,2182,2427">अधिक</WORD>
              <WORD coords="2207,2505,2245,2428">है</WORD>
              <WORD coords="2275,2491,2287,2446">।</WORD>
              <WORD coords="2330,2493,2436,2428">फिर</WORD>
              <WORD coords="2462,2509,2640,2431">राष्ट्रपैय</WORD>
              <WORD coords="2666,2510,2805,2444">नाट्य</WORD>
              <WORD coords="2831,2492,2985,2428">विद्या-</WORD>
            </LINE>
            <LINE>
              <WORD coords="390,2586,478,2536">लय</WORD>
              <WORD coords="504,2587,605,2539">बना</WORD>
              <WORD coords="636,2589,647,2544">।</WORD>
              <WORD coords="692,2595,810,2525">इससे</WORD>
              <WORD coords="836,2587,904,2524">जो</WORD>
              <WORD coords="952,2588,1168,2524">प्रशिक्षित</WORD>
              <WORD coords="1193,2587,1303,2524">लोग</WORD>
              <WORD coords="1343,2593,1463,2523">आये,</WORD>
              <WORD coords="1489,2586,1646,2539">उनका</WORD>
              <WORD coords="1674,2588,1871,2520">योगदान</WORD>
              <WORD coords="1895,2587,2038,2540">नाटक</WORD>
              <WORD coords="2070,2585,2117,2523">के</WORD>
              <WORD coords="2142,2588,2315,2524">विकास</WORD>
              <WORD coords="2342,2587,2385,2525">में</WORD>
              <WORD coords="2438,2601,2532,2541">रहा</WORD>
              <WORD coords="2559,2587,2663,2524">और</WORD>
              <WORD coords="2689,2588,2774,2540">अब</WORD>
              <WORD coords="2801,2588,2870,2525">भी</WORD>
              <WORD coords="2896,2603,2933,2525">है</WORD>
              <WORD coords="2966,2592,2977,2546">।</WORD>
            </LINE>
            <LINE>
              <WORD coords="392,2681,479,2633">अब</WORD>
              <WORD coords="501,2696,574,2636">हर</WORD>
              <WORD coords="599,2684,704,2619">रोज</WORD>
              <WORD coords="729,2682,870,2636">नाटक</WORD>
              <WORD coords="896,2684,1021,2621">देखने</WORD>
              <WORD coords="1046,2683,1114,2620">को</WORD>
              <WORD coords="1139,2684,1287,2620">मिलते</WORD>
              <WORD coords="1310,2696,1348,2620">हैं</WORD>
              <WORD coords="1379,2683,1391,2638">।</WORD>
              <WORD coords="1436,2684,1593,2618">दिल्ली</WORD>
              <WORD coords="1622,2695,1710,2637">एक</WORD>
              <WORD coords="1761,2684,1866,2620">केन्द्र</WORD>
              <WORD coords="1891,2684,1972,2636">बन</WORD>
              <WORD coords="2015,2683,2116,2636">गया</WORD>
              <WORD coords="2141,2696,2179,2620">है</WORD>
              <WORD coords="2208,2684,2222,2638">1</WORD>
              <WORD coords="2268,2691,2347,2638">इस</WORD>
              <WORD coords="2374,2704,2497,2620">दृष्टि</WORD>
              <WORD coords="2521,2684,2566,2621">से</WORD>
              <WORD coords="2589,2682,2652,2619">तो</WORD>
              <WORD coords="2677,2685,2853,2619">विकास</WORD>
              <WORD coords="2879,2704,2983,2638">हुआ</WORD>
            </LINE>
            <LINE>
              <WORD coords="392,2791,427,2715">है</WORD>
              <WORD coords="458,2777,470,2731">।</WORD>
              <WORD coords="502,2797,627,2714">किन्तु</WORD>
              <WORD coords="670,2778,712,2717">मैं</WORD>
              <WORD coords="736,2794,813,2733">यह</WORD>
              <WORD coords="838,2800,921,2715">कहूँ</WORD>
              <WORD coords="947,2779,1018,2716">कि</WORD>
              <WORD coords="1045,2794,1183,2715">हिंदी</WORD>
              <WORD coords="1208,2779,1275,2732">का</WORD>
              <WORD coords="1320,2779,1463,2732">नाटक</WORD>
              <WORD coords="1488,2796,1581,2716">पूरी</WORD>
              <WORD coords="1609,2793,1721,2732">तरह</WORD>
              <WORD coords="1749,2779,1836,2732">जम</WORD>
              <WORD coords="1863,2781,1981,2733">पाया</WORD>
              <WORD coords="2005,2792,2056,2715">है,</WORD>
              <WORD coords="2106,2780,2199,2714">जैसे</WORD>
              <WORD coords="2226,2781,2382,2718">मराठी</WORD>
              <WORD coords="2408,2780,2479,2731">का</WORD>
              <WORD coords="2503,2779,2566,2734">या</WORD>
              <WORD coords="2592,2779,2761,2716">बाँगला</WORD>
              <WORD coords="2789,2778,2860,2733">का</WORD>
              <WORD coords="2885,2780,2983,2721">रंग-</WORD>
            </LINE>
            <LINE>
              <WORD coords="392,2876,482,2814">मंच</WORD>
              <WORD coords="506,2890,557,2813">है,</WORD>
              <WORD coords="587,2877,649,2815">तो</WORD>
              <WORD coords="694,2892,769,2831">यह</WORD>
              <WORD coords="796,2895,999,2814">अत्युक्ति</WORD>
              <WORD coords="1025,2891,1145,2812">होगी</WORD>
              <WORD coords="1169,2877,1179,2831">।</WORD>
              <WORD coords="1227,2882,1349,2814">इसके</WORD>
              <WORD coords="1375,2883,1456,2813">कई</WORD>
              <WORD coords="1483,2877,1631,2831">कारण</WORD>
              <WORD coords="1660,2892,1698,2814">हैं</WORD>
              <WORD coords="1728,2879,1739,2832">।</WORD>
              <WORD coords="1785,2890,1871,2832">एक</WORD>
              <WORD coords="1897,2887,1972,2816">तो,</WORD>
              <WORD coords="2030,2879,2172,2833">शायद</WORD>
              <WORD coords="2196,2880,2352,2814">दिल्लरै</WORD>
              <WORD coords="2379,2879,2426,2816">के</WORD>
              <WORD coords="2471,2880,2623,2813">दर्शकों</WORD>
              <WORD coords="2647,2880,2719,2815">की</WORD>
              <WORD coords="2743,2879,2909,2815">नाटकों</WORD>
              <WORD coords="2934,2878,2981,2815">के</WORD>
            </LINE>
            <LINE>
              <WORD coords="386,2984,495,2908">लिए</WORD>
              <WORD coords="520,2973,626,2911">रुचि</WORD>
              <WORD coords="667,2989,766,2915">नहीं</WORD>
              <WORD coords="791,2988,826,2912">है</WORD>
              <WORD coords="858,2972,868,2927">।</WORD>
              <WORD coords="916,2974,1063,2913">बंगाल</WORD>
              <WORD coords="1104,2973,1147,2911">में</WORD>
              <WORD coords="1172,2976,1281,2909">लोग</WORD>
              <WORD coords="1320,2974,1463,2926">नाटक</WORD>
              <WORD coords="1487,2972,1535,2910">के</WORD>
              <WORD coords="1591,2974,1694,2912">प्रति</WORD>
              <WORD coords="1720,2975,1877,2912">अधिक</WORD>
              <WORD coords="1907,2975,2032,2910">सचेत</WORD>
              <WORD coords="2058,2989,2094,2912">हैं</WORD>
              <WORD coords="2126,2977,2138,2930">है</WORD>
              <WORD coords="2179,2987,2267,2929">एक</WORD>
              <WORD coords="2320,2975,2546,2928">कलात्मक</WORD>
              <WORD coords="2571,2975,2701,2911">विधा</WORD>
              <WORD coords="2754,2972,2802,2909">के</WORD>
              <WORD coords="2828,2975,2912,2930">रूप</WORD>
              <WORD coords="2937,2975,2981,2913">में</WORD>
            </LINE>
            <LINE>
              <WORD coords="389,3068,537,3004">उनको</WORD>
              <WORD coords="567,3076,686,3007">इसमें</WORD>
              <WORD coords="713,3071,792,3025">रस</WORD>
              <WORD coords="818,3069,988,3006">मिलता</WORD>
              <WORD coords="1013,3083,1051,3006">है</WORD>
              <WORD coords="1082,3072,1094,3028">।</WORD>
              <WORD coords="1137,3084,1234,3006">यहाँ</WORD>
              <WORD coords="1258,3073,1416,3006">दिल्ली</WORD>
              <WORD coords="1443,3069,1484,3006">में</WORD>
              <WORD coords="1512,3070,1622,3020">आम</WORD>
              <WORD coords="1649,3071,1817,3007">आदमी</WORD>
              <WORD coords="1841,3070,1982,3023">नाटक</WORD>
              <WORD coords="2009,3069,2057,3005">के</WORD>
              <WORD coords="2084,3072,2184,3009">प्रति</WORD>
              <WORD coords="2211,3072,2414,3010">उदासीन</WORD>
              <WORD coords="2440,3086,2491,3006">है,</WORD>
              <WORD coords="2536,3084,2722,3008">इसलिए</WORD>
              <WORD coords="2771,3093,2980,3007">गिने-चुने</WORD>
            </LINE>
            <LINE>
              <WORD coords="389,3164,497,3101">लोग</WORD>
              <WORD coords="523,3180,581,3102">ही</WORD>
              <WORD coords="605,3180,702,3103">यहाँ</WORD>
              <WORD coords="727,3168,871,3120">नाटक</WORD>
              <WORD coords="927,3166,1052,3101">देखने</WORD>
              <WORD coords="1097,3168,1202,3104">आते</WORD>
              <WORD coords="1230,3180,1266,3105">हैं</WORD>
              <WORD coords="1298,3170,1310,3126">।</WORD>
              <WORD coords="1353,3167,1481,3119">भाषा</WORD>
              <WORD coords="1508,3167,1578,3119">का</WORD>
              <WORD coords="1631,3168,1701,3097">भी</WORD>
              <WORD coords="1725,3170,1858,3122">जरूर</WORD>
              <WORD coords="1883,3169,2033,3122">सवाल</WORD>
              <WORD coords="2058,3184,2096,3105">है</WORD>
              <WORD coords="2128,3173,2140,3127">1</WORD>
              <WORD coords="2183,3172,2340,3105">दिल्ली</WORD>
              <WORD coords="2379,3167,2447,3106">की</WORD>
              <WORD coords="2502,3169,2695,3106">कौन-सी</WORD>
              <WORD coords="2720,3169,2846,3118">भाषा</WORD>
              <WORD coords="2872,3183,2909,3106">है</WORD>
              <WORD coords="2939,3167,2965,3106">?</WORD>
            </LINE>
            <LINE>
              <WORD coords="388,3275,545,3196">हिन्दी,</WORD>
              <WORD coords="574,3281,661,3196">उर्दू</WORD>
              <WORD coords="683,3262,745,3215">या</WORD>
              <WORD coords="773,3278,942,3199">पंजाबी</WORD>
              <WORD coords="970,3257,997,3198">?</WORD>
              <WORD coords="1037,3262,1160,3214">सरल</WORD>
              <WORD coords="1184,3275,1322,3198">हिन्दी</WORD>
              <WORD coords="1345,3277,1384,3199">है</WORD>
              <WORD coords="1409,3260,1472,3215">या</WORD>
              <WORD coords="1496,3262,1659,3196">बिलष्ट</WORD>
              <WORD coords="1686,3276,1826,3198">हिन्दी</WORD>
              <WORD coords="1850,3280,1904,3198">है,</WORD>
              <WORD coords="1960,3265,2111,3217">अथवा</WORD>
              <WORD coords="2134,3282,2402,3202">हिन्दुस्तानी</WORD>
              <WORD coords="2428,3278,2464,3198">है</WORD>
              <WORD coords="2495,3259,2523,3200">?</WORD>
              <WORD coords="2575,3265,2768,3200">कौन-सी</WORD>
              <WORD coords="2798,3214,2801,3209">३</WORD>
              <WORD coords="2832,3284,2979,3218">जुबान</WORD>
            </LINE>
            <LINE>
              <WORD coords="390,3355,551,3293">दिरुली</WORD>
              <WORD coords="579,3357,648,3294">की</WORD>
              <WORD coords="672,3367,722,3291">है,</WORD>
              <WORD coords="754,3362,900,3309">इसका</WORD>
              <WORD coords="924,3356,1147,3291">विश्लेषण</WORD>
              <WORD coords="1173,3356,1255,3309">कर</WORD>
              <WORD coords="1281,3357,1399,3311">पाना</WORD>
              <WORD coords="1424,3356,1503,3293">मेरे</WORD>
              <WORD coords="1543,3370,1653,3294">लिए</WORD>
              <WORD coords="1677,3375,1866,3296">मुदिकल</WORD>
              <WORD coords="1891,3373,1928,3297">है</WORD>
              <WORD coords="1951,3359,1967,3307">।&quot;</WORD>
              <WORD coords="2006,3378,2140,3295">किन्तु</WORD>
              <WORD coords="2163,3360,2251,3313">जब</WORD>
              <WORD coords="2276,3362,2391,3298">कभी</WORD>
              <WORD coords="2417,3372,2578,3296">बढिया</WORD>
              <WORD coords="2629,3359,2775,3297">नाटक</WORD>
              <WORD coords="2801,3374,2923,3297">होता</WORD>
              <WORD coords="2945,3376,2983,3298">है</WORD>
            </LINE>
            <LINE>
              <WORD coords="389,3450,452,3386">तो</WORD>
              <WORD coords="476,3451,609,3385">लोगों</WORD>
              <WORD coords="633,3451,701,3387">को</WORD>
              <WORD coords="727,3452,855,3404">खबर</WORD>
              <WORD coords="878,3453,989,3388">मिल</WORD>
              <WORD coords="1006,3451,1133,3389">जाती</WORD>
              <WORD coords="1149,3466,1187,3388">है</WORD>
              <WORD coords="1212,3455,1317,3389">और</WORD>
              <WORD coords="1340,3452,1380,3391">वे</WORD>
              <WORD coords="1406,3471,1525,3388">पहुँच</WORD>
              <WORD coords="1554,3452,1660,3389">जाते</WORD>
              <WORD coords="1680,3467,1717,3390">हैं</WORD>
              <WORD coords="1739,3454,1750,3409">।</WORD>
              <WORD coords="1783,3455,1888,3393">फिर</WORD>
              <WORD coords="1915,3458,1982,3394">भी</WORD>
              <WORD coords="2007,3459,2164,3391">दिरुली</WORD>
              <WORD coords="2192,3457,2234,3393">में</WORD>
              <WORD coords="2261,3458,2426,3395">रंगमंच</WORD>
              <WORD coords="2455,3458,2615,3393">अधिक</WORD>
              <WORD coords="2641,3457,2858,3391">लोकप्रिय</WORD>
              <WORD coords="2882,3473,2981,3397">नहीं</WORD>
            </LINE>
            <LINE>
              <WORD coords="388,3567,625,3484">हुआ-मुझे</WORD>
              <WORD coords="643,3558,745,3485">ऐसा</WORD>
              <WORD coords="774,3550,918,3503">लगता</WORD>
              <WORD coords="945,3563,980,3485">है</WORD>
              <WORD coords="1012,3549,1023,3502">।</WORD>
              <WORD coords="2050,3500,2054,3498">&quot;</WORD>
              <WORD coords="2813,3500,2819,3496">&quot;</WORD>
            </LINE>
          </PARAGRAPH>
        </REGION>
      </PAGECOLUMN>
      <PAGECOLUMN>
        <REGION>
          <PARAGRAPH>
            <LINE>
              <WORD coords="598,3731,766,3666">आपकी</WORD>
              <WORD coords="795,3749,964,3664">कौन-से</WORD>
              <WORD coords="992,3732,1241,3683">नाटककार</WORD>
              <WORD coords="1260,3744,1381,3667">अच्छे</WORD>
              <WORD coords="1407,3735,1492,3670">लगे</WORD>
              <WORD coords="1523,3733,1551,3669">है</WORD>
              <WORD coords="1624,3696,1630,3692">३</WORD>
            </LINE>
          </PARAGRAPH>
        </REGION>
      </PAGECOLUMN>
      <PAGECOLUMN>
        <REGION>
          <PARAGRAPH>
            <LINE>
              <WORD coords="598,3911,748,3844">राकेश</WORD>
              <WORD coords="775,3909,822,3846">के</WORD>
              <WORD coords="859,3909,1003,3862">नाटक</WORD>
              <WORD coords="1028,3924,1149,3847">अच्छे</WORD>
              <WORD coords="1177,3912,1262,3847">लगे</WORD>
              <WORD coords="1288,3914,1299,3869">।</WORD>
              <WORD coords="1343,3914,1528,3846">धर्मवीर</WORD>
              <WORD coords="1582,3915,1745,3852">भारती</WORD>
              <WORD coords="1769,3916,1837,3868">का</WORD>
              <WORD coords="1863,3917,1996,3868">अम्बा</WORD>
              <WORD coords="2034,3937,2115,3871">युग</WORD>
              <WORD coords="2143,3919,2247,3852">और</WORD>
              <WORD coords="2266,3920,2396,3856">शंकर</WORD>
              <WORD coords="2422,3919,2508,3847">शेष</WORD>
              <WORD coords="2535,3919,2583,3854">के</WORD>
              <WORD coords="2608,3920,2752,3871">नाटक</WORD>
              <WORD coords="2782,3920,2795,3873">है</WORD>
              <WORD coords="2840,3941,2977,3859">दूसरी</WORD>
            </LINE>
            <LINE>
              <WORD coords="391,4008,583,3942">भाषाओं</WORD>
              <WORD coords="601,4006,649,3942">के</WORD>
              <WORD coords="673,4006,940,3942">नाटककारों</WORD>
              <WORD coords="968,4004,1011,3944">में</WORD>
              <WORD coords="1029,4006,1176,3942">विजय</WORD>
              <WORD coords="1201,4026,1409,3945">तेंडुलकर</WORD>
              <WORD coords="1435,4009,1538,3947">और</WORD>
              <WORD coords="1566,4012,1710,3964">बादल</WORD>
              <WORD coords="1736,4012,1917,3965">सरकार</WORD>
              <WORD coords="1942,4012,1989,3948">के</WORD>
              <WORD coords="2005,4013,2148,3967">नाटक</WORD>
              <WORD coords="2175,4016,2244,3952">भी</WORD>
              <WORD coords="2269,4023,2392,3953">अच्छे</WORD>
              <WORD coords="2419,4017,2544,3953">लगते</WORD>
              <WORD coords="2571,4024,2607,3952">हैं</WORD>
              <WORD coords="2638,4017,2651,3971">।</WORD>
            </LINE>
          </PARAGRAPH>
        </REGION>
      </PAGECOLUMN>
      <PAGECOLUMN>
        <REGION>
          <PARAGRAPH>
            <LINE>
              <WORD coords="2648,4283,2969,4208">बदरंग-५२</WORD>
            </LINE>
          </PARAGRAPH>
        </REGION>
      </PAGECOLUMN>
    </HIDDENTEXT>
</OBJECT>
<MAP name="0052.djvu" >
</MAP>
</BODY>
</DjVuXML>
