<?xml version="1.0" encoding="UTF-8"?>
<!DOCTYPE DjVuXML PUBLIC "-//W3C//DTD DjVuXML 1.1//EN" "pubtext/DjVuXML-s.dtd">
<DjVuXML>
<HEAD>file://localhost/home/sriranga/Desktop/suresh/ntg/Volumes/074-076/0219.djvu</HEAD>
<BODY>
<OBJECT data="file://localhost/home/sriranga/Desktop/suresh/ntg/Volumes/074-076/0219.djvu" type="image/x.djvu" height="4381" width="3341" usemap="0219.djvu" >
<PARAM name="DPI" value="400" />
<PARAM name="GAMMA" value="2.200000" />
    <HIDDENTEXT>
      <PAGECOLUMN>
        <REGION>
          <PARAGRAPH>
            <LINE>
              <WORD coords="261,323,387,255">पडती</WORD>
              <WORD coords="414,322,578,254">समीक्षा</WORD>
              <WORD coords="606,316,651,251">में</WORD>
              <WORD coords="680,317,749,256">डॉ.</WORD>
              <WORD coords="790,318,894,252">शर्मा</WORD>
              <WORD coords="923,319,988,271">पर</WORD>
              <WORD coords="1021,319,1163,253">आपने</WORD>
              <WORD coords="1192,322,1270,272">या</WORD>
              <WORD coords="1301,321,1447,254">आरोप</WORD>
              <WORD coords="1476,322,1635,273">लगाया</WORD>
            </LINE>
            <LINE>
              <WORD coords="264,420,318,374">था</WORD>
              <WORD coords="346,418,416,354">कि</WORD>
              <WORD coords="443,417,558,370">उक्त</WORD>
              <WORD coords="587,436,739,369">पुस्तक</WORD>
              <WORD coords="768,415,814,350">में</WORD>
              <WORD coords="842,417,1009,351">निराला</WORD>
              <WORD coords="1039,416,1112,351">को</WORD>
              <WORD coords="1140,417,1206,352">जो</WORD>
              <WORD coords="1236,418,1335,353">छवि</WORD>
              <WORD coords="1364,419,1506,354">सामने</WORD>
              <WORD coords="1536,427,1635,354">जाई</WORD>
            </LINE>
            <LINE>
              <WORD coords="260,524,332,453">गई</WORD>
              <WORD coords="360,527,410,447">है,</WORD>
              <WORD coords="448,518,518,469">वह</WORD>
              <WORD coords="548,516,685,468">असल</WORD>
              <WORD coords="715,516,881,450">निराला</WORD>
              <WORD coords="910,515,983,449">की</WORD>
              <WORD coords="1013,517,1109,449">नहीं</WORD>
              <WORD coords="1138,515,1274,451">वल्कि</WORD>
              <WORD coords="1305,518,1450,451">लेखक</WORD>
              <WORD coords="1479,518,1635,451">निर्मित</WORD>
            </LINE>
            <LINE>
              <WORD coords="260,616,360,552">कवि</WORD>
              <WORD coords="382,613,451,549">की</WORD>
              <WORD coords="473,613,571,548">छवि</WORD>
              <WORD coords="592,616,631,545">है</WORD>
              <WORD coords="652,615,663,567">।</WORD>
              <WORD coords="693,613,854,548">कविता</WORD>
              <WORD coords="877,612,932,547">के</WORD>
              <WORD coords="954,613,1165,547">प्रतिमानों</WORD>
              <WORD coords="1189,613,1260,548">की</WORD>
              <WORD coords="1283,614,1397,549">खोज</WORD>
              <WORD coords="1421,615,1535,549">करते</WORD>
              <WORD coords="1555,633,1634,569">हुए</WORD>
            </LINE>
            <LINE>
              <WORD coords="262,714,424,667">आपका</WORD>
              <WORD coords="445,713,611,645">निष्कर्ष</WORD>
              <WORD coords="637,712,694,664">था</WORD>
              <WORD coords="716,710,789,647">कि</WORD>
              <WORD coords="818,713,1079,646">&quot;मार्क्सवादी</WORD>
              <WORD coords="1100,712,1261,664">नामवर</WORD>
              <WORD coords="1282,715,1382,647">सिह</WORD>
              <WORD coords="1402,714,1475,667">का</WORD>
              <WORD coords="1495,714,1632,649">सर्वनाश</WORD>
            </LINE>
            <LINE>
              <WORD coords="258,814,334,766">रूप</WORD>
              <WORD coords="357,812,396,764">व</WORD>
              <WORD coords="420,812,644,745">आलोचना</WORD>
              <WORD coords="668,830,777,745">ट्टूष्टि</WORD>
              <WORD coords="800,810,872,745">की</WORD>
              <WORD coords="899,812,995,744">और</WORD>
              <WORD coords="1018,811,1171,764">क्रमश:</WORD>
              <WORD coords="1201,829,1350,763">झुकाव</WORD>
              <WORD coords="1372,814,1411,743">है</WORD>
              <WORD coords="1432,813,1467,756">।&quot;</WORD>
              <WORD coords="1495,812,1632,747">यद्यपि</WORD>
            </LINE>
            <LINE>
              <WORD coords="259,912,409,863">नामवर</WORD>
              <WORD coords="435,912,533,844">सिंह</WORD>
              <WORD coords="557,910,601,844">ने</WORD>
              <WORD coords="629,910,773,843">अपनी</WORD>
              <WORD coords="797,927,952,862">पुस्तक</WORD>
              <WORD coords="978,908,1032,844">के</WORD>
              <WORD coords="1058,926,1164,845">दूसरे</WORD>
              <WORD coords="1190,912,1384,843">संस्करण</WORD>
              <WORD coords="1408,912,1453,843">में</WORD>
              <WORD coords="1482,909,1633,845">आपके</WORD>
            </LINE>
            <LINE>
              <WORD coords="260,1010,400,945">आरोप</WORD>
              <WORD coords="433,1008,503,943">को</WORD>
              <WORD coords="536,1027,714,943">झुठलाने</WORD>
              <WORD coords="748,1008,821,943">की</WORD>
              <WORD coords="854,1009,1037,943">कोशिश</WORD>
              <WORD coords="1071,1009,1142,943">को</WORD>
              <WORD coords="1176,1009,1329,943">लेकिन</WORD>
              <WORD coords="1363,1009,1509,962">उनका</WORD>
              <WORD coords="1541,1010,1632,943">तर्क</WORD>
            </LINE>
            <LINE>
              <WORD coords="258,1127,362,1062">ऋत</WORD>
              <WORD coords="380,1107,634,1041">कन्विनर्शिग</WORD>
              <WORD coords="651,1110,744,1041">नहीं</WORD>
              <WORD coords="762,1109,902,1061">लगता</WORD>
              <WORD coords="921,1110,932,1062">।</WORD>
              <WORD coords="957,1119,1127,1042">नेमिजी,</WORD>
              <WORD coords="1151,1107,1249,1061">यया</WORD>
              <WORD coords="1266,1114,1346,1061">इस</WORD>
              <WORD coords="1364,1108,1465,1042">बीच</WORD>
              <WORD coords="1485,1109,1632,1044">आपके</WORD>
            </LINE>
            <LINE>
              <WORD coords="259,1208,409,1140">विचारों</WORD>
              <WORD coords="432,1205,475,1140">में</WORD>
              <WORD coords="500,1209,575,1159">इन</WORD>
              <WORD coords="599,1206,712,1140">दोनों</WORD>
              <WORD coords="737,1207,900,1140">लेखकों</WORD>
              <WORD coords="924,1205,978,1141">के</WORD>
              <WORD coords="1002,1208,1089,1141">बारे</WORD>
              <WORD coords="1115,1207,1160,1140">में</WORD>
              <WORD coords="1184,1214,1289,1140">कोई</WORD>
              <WORD coords="1313,1207,1505,1141">परिवर्तन</WORD>
              <WORD coords="1525,1226,1632,1159">हुआ</WORD>
            </LINE>
            <LINE>
              <WORD coords="258,1311,295,1239">है</WORD>
              <WORD coords="303,1304,324,1260">?</WORD>
            </LINE>
          </PARAGRAPH>
          <PARAGRAPH>
            <LINE>
              <WORD coords="415,1407,667,1339">-धीरे-धीरे</WORD>
              <WORD coords="708,1404,816,1357">जाप</WORD>
              <WORD coords="855,1407,944,1357">कह</WORD>
              <WORD coords="983,1406,1136,1339">सकती</WORD>
              <WORD coords="1175,1407,1214,1337">हैं</WORD>
              <WORD coords="1253,1405,1327,1340">कि</WORD>
              <WORD coords="1364,1406,1408,1337">मैं</WORD>
              <WORD coords="1449,1425,1631,1341">बहुथंधी</WORD>
            </LINE>
            <LINE>
              <WORD coords="259,1506,512,1439">साहित्यकार</WORD>
              <WORD coords="542,1522,587,1438">हूँ</WORD>
              <WORD coords="601,1504,609,1458">।</WORD>
              <WORD coords="643,1505,748,1439">जिन</WORD>
              <WORD coords="776,1504,906,1438">चीजों</WORD>
              <WORD coords="936,1504,980,1438">में</WORD>
              <WORD coords="1010,1505,1100,1438">मेरी</WORD>
              <WORD coords="1129,1504,1236,1439">रुचि</WORD>
              <WORD coords="1264,1507,1305,1436">है</WORD>
              <WORD coords="1333,1504,1394,1438">वो</WORD>
              <WORD coords="1423,1504,1468,1437">मैं</WORD>
              <WORD coords="1497,1506,1633,1457">करता</WORD>
            </LINE>
            <LINE>
              <WORD coords="257,1604,371,1555">रहता</WORD>
              <WORD coords="403,1620,469,1536">हूँ।</WORD>
              <WORD coords="503,1603,784,1536">परिस्तितियत्</WORD>
              <WORD coords="819,1603,882,1538">भी</WORD>
              <WORD coords="913,1603,1048,1537">उसके</WORD>
              <WORD coords="1080,1611,1184,1537">लिए</WORD>
              <WORD coords="1215,1610,1409,1536">उत्तरदायी</WORD>
              <WORD coords="1440,1605,1481,1535">हैं</WORD>
              <WORD coords="1501,1604,1509,1557">।</WORD>
              <WORD coords="1545,1604,1631,1538">मेरी</WORD>
            </LINE>
            <LINE>
              <WORD coords="258,1701,394,1653">नाटक</WORD>
              <WORD coords="425,1700,468,1636">में</WORD>
              <WORD coords="500,1701,634,1636">उतनी</WORD>
              <WORD coords="666,1701,774,1636">रुचि</WORD>
              <WORD coords="804,1701,919,1636">कभी</WORD>
              <WORD coords="952,1704,1047,1636">नहीं</WORD>
              <WORD coords="1083,1701,1144,1637">थी</WORD>
              <WORD coords="1165,1702,1174,1656">।</WORD>
              <WORD coords="1214,1712,1310,1635">थोडे</WORD>
              <WORD coords="1343,1720,1457,1653">बहुत</WORD>
              <WORD coords="1488,1700,1632,1654">नाटक</WORD>
            </LINE>
            <LINE>
              <WORD coords="258,1798,409,1751">बचपन</WORD>
              <WORD coords="437,1807,491,1733">में,</WORD>
              <WORD coords="522,1799,616,1751">याद</WORD>
              <WORD coords="646,1808,748,1734">नहीं,</WORD>
              <WORD coords="781,1808,889,1733">किए</WORD>
              <WORD coords="917,1801,1012,1733">होंगे</WORD>
              <WORD coords="1032,1800,1040,1752">।</WORD>
              <WORD coords="1072,1816,1207,1751">नाट्य</WORD>
              <WORD coords="1234,1800,1319,1737">संघ</WORD>
              <WORD coords="1347,1799,1401,1734">के</WORD>
              <WORD coords="1430,1799,1632,1733">आदोलन</WORD>
            </LINE>
            <LINE>
              <WORD coords="258,1898,303,1830">से</WORD>
              <WORD coords="330,1898,414,1831">मेरा</WORD>
              <WORD coords="443,1898,569,1834">संबंध</WORD>
              <WORD coords="596,1899,680,1850">रहा</WORD>
              <WORD coords="711,1924,794,1849">थगु</WORD>
              <WORD coords="815,1897,950,1832">उसके</WORD>
              <WORD coords="977,1917,1073,1850">कुछ</WORD>
              <WORD coords="1101,1898,1254,1832">सक्रिय</WORD>
              <WORD coords="1281,1897,1390,1851">काम</WORD>
              <WORD coords="1418,1898,1466,1833">से</WORD>
              <WORD coords="1497,1898,1559,1833">भी</WORD>
              <WORD coords="1588,1897,1631,1830">में</WORD>
            </LINE>
            <LINE>
              <WORD coords="256,2015,355,1949">जुडा</WORD>
              <WORD coords="379,1998,460,1948">रहा</WORD>
              <WORD coords="480,1996,489,1950">।</WORD>
              <WORD coords="518,1997,584,1949">पर</WORD>
              <WORD coords="610,1996,731,1931">निजी</WORD>
              <WORD coords="758,1998,845,1928">तीर</WORD>
              <WORD coords="869,1997,938,1949">पर</WORD>
              <WORD coords="964,1996,1023,1931">वो</WORD>
              <WORD coords="1048,1997,1136,1930">मेरा</WORD>
              <WORD coords="1162,1997,1299,1932">विषय</WORD>
              <WORD coords="1324,1998,1416,1931">नहीं</WORD>
              <WORD coords="1446,1997,1505,1949">था</WORD>
              <WORD coords="1526,1997,1534,1950">।</WORD>
              <WORD coords="1563,1998,1630,1950">पर</WORD>
            </LINE>
            <LINE>
              <WORD coords="258,2113,348,2048">कुछ</WORD>
              <WORD coords="370,2103,471,2028">ऐसा</WORD>
              <WORD coords="494,2113,599,2048">हुआ</WORD>
              <WORD coords="624,2094,694,2029">कि</WORD>
              <WORD coords="718,2094,761,2027">में</WORD>
              <WORD coords="786,2094,874,2048">जब</WORD>
              <WORD coords="898,2095,1041,2030">दिल्ली</WORD>
              <WORD coords="1067,2095,1195,2047">जाया</WORD>
              <WORD coords="1218,2095,1279,2029">तो</WORD>
              <WORD coords="1303,2096,1384,2028">मैंने</WORD>
              <WORD coords="1407,2095,1516,2048">काम</WORD>
              <WORD coords="1540,2113,1631,2029">दूँढा</WORD>
            </LINE>
            <LINE>
              <WORD coords="258,2195,393,2128">संगीत</WORD>
              <WORD coords="421,2195,563,2146">नाटक</WORD>
              <WORD coords="594,2195,801,2128">अकादेमी</WORD>
              <WORD coords="832,2195,877,2128">में</WORD>
              <WORD coords="906,2194,968,2127">तो</WORD>
              <WORD coords="995,2195,1121,2128">उसमें</WORD>
              <WORD coords="1151,2212,1251,2146">नृत्य</WORD>
              <WORD coords="1282,2196,1380,2126">और</WORD>
              <WORD coords="1409,2195,1549,2129">संगीत</WORD>
              <WORD coords="1577,2195,1631,2129">के</WORD>
            </LINE>
            <LINE>
              <WORD coords="258,2294,447,2246">जानकार</WORD>
              <WORD coords="471,2293,575,2228">लोग</WORD>
              <WORD coords="602,2293,645,2227">थे</WORD>
              <WORD coords="666,2293,674,2246">।</WORD>
              <WORD coords="703,2294,855,2230">रंगमंच</WORD>
              <WORD coords="879,2292,934,2227">के</WORD>
              <WORD coords="959,2295,1046,2228">बोरे</WORD>
              <WORD coords="1070,2292,1114,2227">में</WORD>
              <WORD coords="1139,2299,1242,2226">कोई</WORD>
              <WORD coords="1267,2293,1426,2246">जानता</WORD>
              <WORD coords="1449,2295,1542,2228">नहीं</WORD>
              <WORD coords="1571,2294,1631,2246">था</WORD>
            </LINE>
            <LINE>
              <WORD coords="257,2391,368,2344">खास</WORD>
              <WORD coords="390,2392,449,2326">तो</WORD>
              <WORD coords="472,2409,624,2326">मुझको</WORD>
              <WORD coords="645,2394,723,2344">यह</WORD>
              <WORD coords="748,2393,838,2344">भार</WORD>
              <WORD coords="861,2392,973,2327">दिया</WORD>
              <WORD coords="996,2391,1096,2344">गया</WORD>
              <WORD coords="1118,2391,1189,2327">कि</WORD>
              <WORD coords="1211,2392,1361,2328">रंगमंच</WORD>
              <WORD coords="1384,2392,1486,2326">वाले</WORD>
              <WORD coords="1507,2395,1631,2326">हिस्से</WORD>
            </LINE>
            <LINE>
              <WORD coords="258,2488,326,2423">की</WORD>
              <WORD coords="358,2490,547,2422">देखभाल</WORD>
              <WORD coords="580,2488,624,2422">मैँ</WORD>
              <WORD coords="658,2489,754,2423">करदें</WORD>
              <WORD coords="775,2489,784,2442">।</WORD>
              <WORD coords="824,2490,943,2442">अगर</WORD>
              <WORD coords="976,2489,1022,2422">मैं</WORD>
              <WORD coords="1056,2490,1248,2423">देखभाल</WORD>
              <WORD coords="1282,2490,1377,2423">करदें</WORD>
              <WORD coords="1412,2490,1472,2425">तो</WORD>
              <WORD coords="1505,2496,1631,2425">इसके</WORD>
            </LINE>
            <LINE>
              <WORD coords="258,2596,357,2521">लिए</WORD>
              <WORD coords="378,2606,464,2523">मुझे</WORD>
              <WORD coords="484,2596,575,2540">एक</WORD>
              <WORD coords="596,2590,700,2541">तरह</WORD>
              <WORD coords="721,2588,768,2522">से</WORD>
              <WORD coords="789,2589,916,2519">तैयार</WORD>
              <WORD coords="936,2589,1048,2522">होना</WORD>
              <WORD coords="1069,2598,1176,2541">पडा,</WORD>
              <WORD coords="1199,2599,1325,2521">पढाई</WORD>
              <WORD coords="1346,2588,1416,2523">की</WORD>
              <WORD coords="1437,2595,1511,2521">गईं</WORD>
              <WORD coords="1534,2589,1631,2521">और</WORD>
            </LINE>
            <LINE>
              <WORD coords="257,2686,374,2619">उसमें</WORD>
              <WORD coords="390,2687,491,2621">रुचि</WORD>
              <WORD coords="511,2687,595,2620">लेने</WORD>
              <WORD coords="612,2686,714,2639">लगा</WORD>
              <WORD coords="733,2685,777,2618">में</WORD>
              <WORD coords="795,2686,803,2641">।</WORD>
              <WORD coords="827,2703,948,2639">दूसरा</WORD>
              <WORD coords="967,2687,1106,2621">संयोग</WORD>
              <WORD coords="1123,2689,1203,2637">यह</WORD>
              <WORD coords="1217,2704,1321,2639">हुआ</WORD>
              <WORD coords="1341,2686,1410,2621">कि</WORD>
              <WORD coords="1430,2687,1630,2622">अकादेमी</WORD>
            </LINE>
            <LINE>
              <WORD coords="258,2784,300,2718">ने</WORD>
              <WORD coords="328,2803,489,2719">मुझको,</WORD>
              <WORD coords="525,2786,665,2719">संगीत</WORD>
              <WORD coords="695,2784,839,2737">नाटक</WORD>
              <WORD coords="872,2785,1080,2720">अकादेमी</WORD>
              <WORD coords="1111,2794,1167,2720">में,</WORD>
              <WORD coords="1201,2784,1289,2737">जब</WORD>
              <WORD coords="1319,2784,1442,2720">उसने</WORD>
              <WORD coords="1470,2792,1632,2721">राष्टीय</WORD>
            </LINE>
            <LINE>
              <WORD coords="258,2899,388,2835">नाट्य</WORD>
              <WORD coords="417,2882,616,2819">विद्यालय</WORD>
              <WORD coords="645,2882,716,2818">की</WORD>
              <WORD coords="747,2883,929,2835">स्थापना</WORD>
              <WORD coords="959,2883,1031,2819">क्री</WORD>
              <WORD coords="1063,2883,1123,2818">तो</WORD>
              <WORD coords="1154,2902,1285,2818">मुझसे</WORD>
              <WORD coords="1316,2884,1420,2836">कहा</WORD>
              <WORD coords="1449,2882,1520,2818">कि</WORD>
              <WORD coords="1550,2901,1631,2836">तुम</WORD>
            </LINE>
            <LINE>
              <WORD coords="258,2987,401,2916">इसकी</WORD>
              <WORD coords="443,2981,645,2915">देखभाल</WORD>
              <WORD coords="685,2982,787,2916">करों</WORD>
              <WORD coords="810,2980,819,2935">।</WORD>
              <WORD coords="864,2991,971,2934">एक,</WORD>
              <WORD coords="1016,2981,1129,2916">जिसे</WORD>
              <WORD coords="1173,2982,1319,2933">कहना</WORD>
              <WORD coords="1359,2990,1518,2916">चाहिए</WORD>
              <WORD coords="1559,2981,1631,2916">कि</WORD>
            </LINE>
            <LINE>
              <WORD coords="258,3079,523,3014">उत्तरदायित्व</WORD>
              <WORD coords="551,3080,621,3013">मेरे</WORD>
              <WORD coords="649,3079,769,3031">उपर</WORD>
              <WORD coords="799,3078,871,3030">जा&quot;</WORD>
              <WORD coords="899,3079,999,3030">गया</WORD>
              <WORD coords="1020,3079,1028,3033">।</WORD>
              <WORD coords="1064,3079,1162,3010">और</WORD>
              <WORD coords="1190,3080,1287,3013">फिर</WORD>
              <WORD coords="1315,3079,1358,3011">मैं</WORD>
              <WORD coords="1388,3080,1479,3012">वहाँ</WORD>
              <WORD coords="1507,3090,1631,3011">पकाई</WORD>
            </LINE>
            <LINE>
              <WORD coords="259,3176,326,3128">का</WORD>
              <WORD coords="359,3176,466,3129">काम</WORD>
              <WORD coords="499,3176,625,3111">किया</WORD>
              <WORD coords="660,3177,758,3109">और</WORD>
              <WORD coords="792,3176,859,3112">जो</WORD>
              <WORD coords="898,3178,1042,3129">शासन</WORD>
              <WORD coords="1077,3176,1222,3111">संबन्धी</WORD>
              <WORD coords="1255,3175,1363,3129">काम</WORD>
              <WORD coords="1401,3175,1462,3111">भी</WORD>
              <WORD coords="1496,3176,1630,3128">करना</WORD>
            </LINE>
            <LINE>
              <WORD coords="259,3284,386,3227">पड़ता</WORD>
              <WORD coords="416,3284,487,3228">था,</WORD>
              <WORD coords="516,3274,639,3209">उसमें</WORD>
              <WORD coords="666,3275,754,3209">मेरी</WORD>
              <WORD coords="780,3293,895,3227">वहुत</WORD>
              <WORD coords="921,3273,1027,3211">रुचि</WORD>
              <WORD coords="1058,3274,1118,3210">थी</WORD>
              <WORD coords="1143,3276,1238,3209">नहीं</WORD>
              <WORD coords="1258,3275,1266,3228">।</WORD>
              <WORD coords="1298,3274,1394,3209">फिर</WORD>
              <WORD coords="1420,3273,1501,3207">मैंने</WORD>
              <WORD coords="1528,3276,1630,3227">कहा</WORD>
            </LINE>
            <LINE>
              <WORD coords="260,3371,328,3307">कि</WORD>
              <WORD coords="353,3380,512,3308">राष्टीय</WORD>
              <WORD coords="538,3388,672,3325">नाट्य</WORD>
              <WORD coords="698,3372,899,3308">विद्यालय</WORD>
              <WORD coords="925,3371,969,3306">में</WORD>
              <WORD coords="996,3382,1126,3307">पढाने</WORD>
              <WORD coords="1154,3371,1224,3325">का</WORD>
              <WORD coords="1251,3371,1359,3324">काम</WORD>
              <WORD coords="1387,3371,1545,3307">मिलेगा</WORD>
              <WORD coords="1571,3371,1631,3306">तो</WORD>
            </LINE>
            <LINE>
              <WORD coords="259,3470,394,3421">ज्यादा</WORD>
              <WORD coords="418,3471,552,3424">अच्छा</WORD>
              <WORD coords="575,3473,614,3403">है</WORD>
              <WORD coords="634,3471,642,3425">।</WORD>
              <WORD coords="670,3470,729,3405">तो</WORD>
              <WORD coords="751,3472,843,3405">यहीं</WORD>
              <WORD coords="866,3480,975,3406">फिर,</WORD>
              <WORD coords="1001,3471,1104,3401">कहीं</WORD>
              <WORD coords="1127,3472,1220,3405">नहीं</WORD>
              <WORD coords="1244,3469,1342,3423">गया</WORD>
              <WORD coords="1365,3470,1408,3401">मैं</WORD>
              <WORD coords="1432,3472,1630,3422">अवकाश</WORD>
            </LINE>
            <LINE>
              <WORD coords="258,3567,301,3520">न</WORD>
              <WORD coords="325,3567,438,3521">प्राप्त</WORD>
              <WORD coords="463,3570,580,3503">करने</WORD>
              <WORD coords="606,3568,696,3522">तक</WORD>
              <WORD coords="717,3569,725,3523">।</WORD>
              <WORD coords="754,3568,842,3521">जब</WORD>
              <WORD coords="868,3569,1005,3521">ज्यादा</WORD>
              <WORD coords="1032,3569,1142,3521">काम</WORD>
              <WORD coords="1167,3578,1263,3521">बढा</WORD>
              <WORD coords="1287,3568,1430,3521">नाटक</WORD>
              <WORD coords="1455,3566,1525,3521">का</WORD>
              <WORD coords="1551,3567,1631,3521">तब</WORD>
            </LINE>
            <LINE>
              <WORD coords="261,3666,356,3597">और</WORD>
              <WORD coords="388,3665,448,3601">भी</WORD>
              <WORD coords="476,3676,607,3618">पढ़ना</WORD>
              <WORD coords="635,3677,729,3619">पहा</WORD>
              <WORD coords="759,3668,857,3598">और</WORD>
              <WORD coords="885,3666,969,3619">उस</WORD>
              <WORD coords="999,3666,1146,3600">स्थिति</WORD>
              <WORD coords="1173,3665,1218,3600">में</WORD>
              <WORD coords="1246,3666,1417,3601">लिखना</WORD>
              <WORD coords="1448,3664,1510,3600">भी</WORD>
              <WORD coords="1537,3675,1631,3618">पड़ा</WORD>
            </LINE>
            <LINE>
              <WORD coords="259,3765,357,3695">और</WORD>
              <WORD coords="394,3764,459,3698">जो</WORD>
              <WORD coords="496,3764,629,3698">लिखा</WORD>
              <WORD coords="666,3764,829,3699">क्योंकि</WORD>
              <WORD coords="866,3765,909,3696">मैं</WORD>
              <WORD coords="946,3773,1112,3698">एकक्वेदो</WORD>
              <WORD coords="1149,3766,1252,3717">तरह</WORD>
              <WORD coords="1288,3763,1360,3716">का</WORD>
              <WORD coords="1399,3782,1631,3716">अनुशासन</WORD>
            </LINE>
            <LINE>
              <WORD coords="260,3864,380,3796">लेकर</WORD>
              <WORD coords="415,3862,540,3815">जाया</WORD>
              <WORD coords="577,3862,638,3814">था</WORD>
              <WORD coords="671,3863,834,3798">कविता</WORD>
              <WORD coords="867,3863,938,3816">का</WORD>
              <WORD coords="973,3863,1071,3795">और</WORD>
              <WORD coords="1105,3864,1202,3798">फिर</WORD>
              <WORD coords="1236,3862,1434,3815">उपन्यास</WORD>
              <WORD coords="1468,3862,1630,3797">समीक्षा</WORD>
            </LINE>
            <LINE>
              <WORD coords="261,3960,329,3913">का</WORD>
              <WORD coords="349,3961,358,3915">।</WORD>
              <WORD coords="384,3961,443,3895">तो</WORD>
              <WORD coords="465,3961,544,3913">उन</WORD>
              <WORD coords="566,3960,676,3895">दोनों</WORD>
              <WORD coords="698,3962,771,3914">का</WORD>
              <WORD coords="791,3961,963,3896">उपयोग</WORD>
              <WORD coords="986,3961,1067,3894">मैंने</WORD>
              <WORD coords="1089,3978,1354,3895">नाट्यलेखन</WORD>
              <WORD coords="1376,3960,1446,3896">की</WORD>
              <WORD coords="1469,3961,1631,3895">समीक्षा</WORD>
            </LINE>
          </PARAGRAPH>
        </REGION>
      </PAGECOLUMN>
      <PAGECOLUMN>
        <REGION>
          <PARAGRAPH>
            <LINE>
              <WORD coords="263,4159,438,4083">सितंबर,</WORD>
              <WORD coords="473,4151,501,4104">तो</WORD>
              <WORD coords="508,4141,541,4109">०</WORD>
              <WORD coords="549,4141,581,4110">०</WORD>
              <WORD coords="590,4156,618,4102">२</WORD>
            </LINE>
          </PARAGRAPH>
        </REGION>
      </PAGECOLUMN>
      <PAGECOLUMN>
        <REGION>
          <PARAGRAPH>
            <LINE>
              <WORD coords="1709,322,1753,257">में</WORD>
              <WORD coords="1771,323,1896,257">किया</WORD>
              <WORD coords="1916,325,1924,277">।</WORD>
              <WORD coords="1950,324,2119,257">लिखना</WORD>
              <WORD coords="2139,335,2272,277">बढ़ता</WORD>
              <WORD coords="2292,328,2346,260">ही</WORD>
              <WORD coords="2367,325,2465,277">गया</WORD>
              <WORD coords="2487,328,2583,260">फिर</WORD>
              <WORD coords="2603,327,2682,258">मैंने</WORD>
              <WORD coords="2702,329,2806,261">हिंदी</WORD>
              <WORD coords="2827,328,2869,260">में</WORD>
              <WORD coords="2889,337,3086,261">समीक्षाएँ</WORD>
            </LINE>
            <LINE>
              <WORD coords="1708,421,1841,355">लिखी</WORD>
              <WORD coords="1861,423,1869,376">।</WORD>
              <WORD coords="1898,422,2050,356">अंग्रेजी</WORD>
              <WORD coords="2076,422,2119,355">में</WORD>
              <WORD coords="2150,440,2394,356">&apos;स्टेट्समैन&apos;</WORD>
              <WORD coords="2425,424,2468,359">में</WORD>
              <WORD coords="2493,428,2698,361">दस&apos;-पंद्रह</WORD>
              <WORD coords="2721,425,2817,358">वर्षों</WORD>
              <WORD coords="2841,426,2930,378">तक</WORD>
              <WORD coords="2953,443,3086,378">नाट्य</WORD>
            </LINE>
            <LINE>
              <WORD coords="1709,520,1873,453">समीक्षा</WORD>
              <WORD coords="1902,520,1987,472">सब</WORD>
              <WORD coords="2017,522,2188,455">लिखता</WORD>
              <WORD coords="2216,524,2298,473">रहा</WORD>
              <WORD coords="2319,523,2328,476">।</WORD>
              <WORD coords="2363,523,2423,454">तो</WORD>
              <WORD coords="2452,524,2549,456">फिर</WORD>
              <WORD coords="2578,522,2667,475">जब</WORD>
              <WORD coords="2694,525,2864,458">लिखना</WORD>
              <WORD coords="2892,543,2997,475">हुआ</WORD>
              <WORD coords="3027,525,3085,458">तो</WORD>
            </LINE>
            <LINE>
              <WORD coords="1708,617,1789,549">मैंने</WORD>
              <WORD coords="1821,619,1926,550">देखा</WORD>
              <WORD coords="1958,617,2028,551">कि</WORD>
              <WORD coords="2060,618,2204,570">नाटक</WORD>
              <WORD coords="2235,619,2289,552">के</WORD>
              <WORD coords="2321,620,2472,556">रंगमंच</WORD>
              <WORD coords="2505,619,2558,553">के</WORD>
              <WORD coords="2589,622,2676,554">बोरे</WORD>
              <WORD coords="2709,620,2752,555">में</WORD>
              <WORD coords="2784,628,2885,554">कोई</WORD>
              <WORD coords="2917,623,3085,556">लिखता</WORD>
            </LINE>
            <LINE>
              <WORD coords="1708,718,1762,649">ही</WORD>
              <WORD coords="1788,718,1881,651">नहीं</WORD>
              <WORD coords="1907,718,1947,647">है</WORD>
              <WORD coords="1966,717,1975,669">।</WORD>
              <WORD coords="2007,718,2105,648">और</WORD>
              <WORD coords="2133,728,2276,651">देखिए</WORD>
              <WORD coords="2302,717,2363,670">ना</WORD>
              <WORD coords="2390,718,2544,652">जिदगी</WORD>
              <WORD coords="2571,719,2668,650">कैसे</WORD>
              <WORD coords="2694,720,2850,653">संयोगों</WORD>
              <WORD coords="2879,721,2924,654">से</WORD>
              <WORD coords="2950,720,3083,655">जानती</WORD>
            </LINE>
            <LINE>
              <WORD coords="1706,822,1757,745">है,</WORD>
              <WORD coords="1794,817,1865,746">मेरे</WORD>
              <WORD coords="1897,823,1990,766">एक</WORD>
              <WORD coords="2022,814,2124,749">मित्र</WORD>
              <WORD coords="2161,815,2205,749">थे</WORD>
              <WORD coords="2238,834,2429,767">रामबाबू</WORD>
              <WORD coords="2454,817,2564,768">लाल</WORD>
              <WORD coords="2598,819,2765,768">हाथरस</WORD>
              <WORD coords="2797,817,2849,751">के</WORD>
              <WORD coords="2883,836,2995,770">वहुत</WORD>
              <WORD coords="3029,822,3082,752">ही</WORD>
            </LINE>
            <LINE>
              <WORD coords="1707,912,1850,846">सिंपल</WORD>
              <WORD coords="1880,921,1935,846">थे,</WORD>
              <WORD coords="1966,915,2119,846">उन्होंने</WORD>
              <WORD coords="2146,922,2239,866">एक</WORD>
              <WORD coords="2266,932,2354,866">बृज</WORD>
              <WORD coords="2380,915,2495,866">कला</WORD>
              <WORD coords="2521,916,2609,849">केंद्र</WORD>
              <WORD coords="2634,916,2733,867">नाम</WORD>
              <WORD coords="2759,916,2830,849">की</WORD>
              <WORD coords="2857,916,2988,853">संस्था</WORD>
              <WORD coords="3014,916,3084,869">का</WORD>
            </LINE>
            <LINE>
              <WORD coords="1708,1011,1916,945">उपयोजन</WORD>
              <WORD coords="1940,1011,2065,946">किया</WORD>
              <WORD coords="2086,1012,2095,966">।</WORD>
              <WORD coords="2126,1011,2253,946">अपने</WORD>
              <WORD coords="2277,1015,2371,945">यहाँ</WORD>
              <WORD coords="2392,1013,2401,966">।</WORD>
              <WORD coords="2430,1012,2490,947">तो</WORD>
              <WORD coords="2515,1015,2585,947">मेरे</WORD>
              <WORD coords="2610,1013,2764,948">घनिष्ट</WORD>
              <WORD coords="2788,1015,2888,948">मित्र</WORD>
              <WORD coords="2915,1014,2958,948">थे</WORD>
              <WORD coords="2979,1016,2987,969">।</WORD>
              <WORD coords="3015,1017,3083,948">मेरे</WORD>
            </LINE>
            <LINE>
              <WORD coords="1706,1120,1783,1044">बड़े</WORD>
              <WORD coords="1817,1117,1913,1042">भाई</WORD>
              <WORD coords="1943,1110,2013,1045">की</WORD>
              <WORD coords="2045,1113,2149,1062">तरह</WORD>
              <WORD coords="2183,1110,2227,1044">थे</WORD>
              <WORD coords="2248,1110,2256,1065">।</WORD>
              <WORD coords="2290,1112,2444,1045">उन्होंने</WORD>
              <WORD coords="2476,1130,2607,1046">मुझसे</WORD>
              <WORD coords="2637,1115,2741,1064">कहा</WORD>
              <WORD coords="2772,1111,2843,1046">कि</WORD>
              <WORD coords="2873,1115,2963,1046">वहाँ</WORD>
              <WORD coords="2993,1121,3084,1065">एक</WORD>
            </LINE>
            <LINE>
              <WORD coords="1705,1207,1804,1160">बात</WORD>
              <WORD coords="1829,1208,1924,1143">उठी</WORD>
              <WORD coords="1952,1207,2022,1142">कि</WORD>
              <WORD coords="2048,1217,2139,1160">एक</WORD>
              <WORD coords="2166,1209,2246,1161">पत्र</WORD>
              <WORD coords="2274,1209,2461,1143">निकाला</WORD>
              <WORD coords="2487,1219,2592,1161">जाए</WORD>
              <WORD coords="2619,1228,2706,1162">बृज</WORD>
              <WORD coords="2731,1210,2845,1162">कला</WORD>
              <WORD coords="2871,1212,2956,1144">केंद्र</WORD>
              <WORD coords="2981,1211,3052,1162">का</WORD>
              <WORD coords="3071,1212,3080,1164">।</WORD>
            </LINE>
            <LINE>
              <WORD coords="1705,1306,1766,1241">तो</WORD>
              <WORD coords="1797,1325,1928,1241">मुझसे</WORD>
              <WORD coords="1960,1309,2031,1240">मेरे</WORD>
              <WORD coords="2064,1308,2165,1242">मित्र</WORD>
              <WORD coords="2196,1311,2322,1242">कहने</WORD>
              <WORD coords="2354,1308,2442,1242">लगे</WORD>
              <WORD coords="2473,1308,2544,1241">कि</WORD>
              <WORD coords="2576,1328,2658,1260">तुम</WORD>
              <WORD coords="2689,1308,2786,1243">क्यों</WORD>
              <WORD coords="2817,1311,2909,1244">नहीं</WORD>
              <WORD coords="2942,1315,3084,1244">इसको</WORD>
            </LINE>
            <LINE>
              <WORD coords="1705,1407,1822,1339">करते</WORD>
              <WORD coords="1843,1406,1851,1359">।</WORD>
              <WORD coords="1883,1405,1965,1338">मैंने</WORD>
              <WORD coords="1993,1408,2098,1358">कहा</WORD>
              <WORD coords="2127,1406,2198,1341">कि</WORD>
              <WORD coords="2226,1405,2269,1338">मैं</WORD>
              <WORD coords="2298,1408,2418,1341">करने</WORD>
              <WORD coords="2446,1406,2517,1341">को</WORD>
              <WORD coords="2546,1408,2606,1342">तो</WORD>
              <WORD coords="2635,1410,2760,1338">तैयार</WORD>
              <WORD coords="2789,1425,2837,1340">हूँ</WORD>
              <WORD coords="2869,1409,2937,1360">पर</WORD>
              <WORD coords="2967,1409,3082,1360">अगर</WORD>
            </LINE>
            <LINE>
              <WORD coords="1705,1505,1828,1439">उसमें</WORD>
              <WORD coords="1855,1505,1900,1439">ये</WORD>
              <WORD coords="1926,1506,2059,1441">संस्था</WORD>
              <WORD coords="2087,1507,2269,1439">हस्तक्षेप</WORD>
              <WORD coords="2296,1506,2357,1457">ना</WORD>
              <WORD coords="2386,1507,2465,1440">को</WORD>
              <WORD coords="2493,1505,2553,1439">तो</WORD>
              <WORD coords="2580,1505,2624,1438">मैं</WORD>
              <WORD coords="2651,1507,2777,1437">तैयार</WORD>
              <WORD coords="2804,1524,2849,1439">हूँ</WORD>
              <WORD coords="2862,1507,2871,1460">।</WORD>
              <WORD coords="2901,1506,2961,1441">तो</WORD>
              <WORD coords="2988,1508,3083,1442">फिर</WORD>
            </LINE>
            <LINE>
              <WORD coords="1705,1605,1783,1556">यह</WORD>
              <WORD coords="1804,1603,1890,1556">सब</WORD>
              <WORD coords="1911,1622,2016,1556">हुआ</WORD>
              <WORD coords="2037,1604,2046,1558">।</WORD>
              <WORD coords="2071,1604,2222,1556">उसका</WORD>
              <WORD coords="2247,1604,2310,1538">भी</WORD>
              <WORD coords="2335,1604,2463,1538">अपने</WORD>
              <WORD coords="2488,1604,2631,1539">आपमें</WORD>
              <WORD coords="2652,1612,2745,1556">एक</WORD>
              <WORD coords="2767,1613,2861,1557">बड़ा</WORD>
              <WORD coords="2883,1605,3083,1539">दिलचस्प</WORD>
            </LINE>
            <LINE>
              <WORD coords="1705,1707,1889,1637">इतिहास</WORD>
              <WORD coords="1916,1704,1956,1634">है</WORD>
              <WORD coords="1984,1701,2052,1637">जो</WORD>
              <WORD coords="2082,1711,2174,1655">एक</WORD>
              <WORD coords="2203,1719,2270,1636">पूरे</WORD>
              <WORD coords="2299,1702,2399,1636">लेख</WORD>
              <WORD coords="2428,1701,2501,1655">का</WORD>
              <WORD coords="2529,1703,2591,1655">या</WORD>
              <WORD coords="2620,1703,2755,1641">संवाद</WORD>
              <WORD coords="2784,1703,2854,1654">का</WORD>
              <WORD coords="2882,1704,3018,1637">विषय</WORD>
              <WORD coords="3044,1706,3084,1635">है</WORD>
            </LINE>
            <LINE>
              <WORD coords="1706,1798,1775,1734">कि</WORD>
              <WORD coords="1795,1800,1888,1730">कैसे</WORD>
              <WORD coords="1908,1801,1982,1752">वह</WORD>
              <WORD coords="2001,1798,2096,1752">बना</WORD>
              <WORD coords="2117,1800,2289,1735">जिसका</WORD>
              <WORD coords="2310,1799,2388,1732">मैंने</WORD>
              <WORD coords="2409,1799,2523,1735">जिक्र</WORD>
              <WORD coords="2543,1800,2667,1735">जिया</WORD>
              <WORD coords="2684,1803,2724,1732">है</WORD>
              <WORD coords="2742,1800,2751,1754">।</WORD>
              <WORD coords="2775,1808,2865,1753">एक</WORD>
              <WORD coords="2884,1803,3084,1735">विशेषांक</WORD>
            </LINE>
            <LINE>
              <WORD coords="1706,1899,1873,1833">निकला</WORD>
              <WORD coords="1910,1898,1970,1850">था</WORD>
              <WORD coords="2003,1899,2201,1832">पचासबॉं</WORD>
              <WORD coords="2237,1898,2368,1835">अंका</WORD>
              <WORD coords="2406,1898,2502,1830">कैसे</WORD>
              <WORD coords="2536,1900,2611,1850">वह</WORD>
              <WORD coords="2649,1916,2737,1850">शुरु</WORD>
              <WORD coords="2770,1916,2876,1850">हुआ</WORD>
              <WORD coords="2912,1897,2972,1850">था</WORD>
              <WORD coords="3005,1905,3083,1851">इस</WORD>
            </LINE>
            <LINE>
              <WORD coords="1705,1997,1803,1950">बात</WORD>
              <WORD coords="1835,1998,1906,1950">का</WORD>
              <WORD coords="1938,1997,2052,1932">लिक</WORD>
              <WORD coords="2084,1998,2167,1929">मैंने</WORD>
              <WORD coords="2200,1998,2328,1932">किया</WORD>
              <WORD coords="2360,2000,2400,1929">है</WORD>
              <WORD coords="2432,2000,2535,1932">कहीं</WORD>
              <WORD coords="2569,1999,2735,1933">विस्तार</WORD>
              <WORD coords="2769,1999,2816,1931">से</WORD>
              <WORD coords="2836,1999,2845,1953">।</WORD>
            </LINE>
            <LINE>
              <WORD coords="1861,2097,2105,2030">रामविलास</WORD>
              <WORD coords="2133,2098,2236,2028">शर्मा</WORD>
              <WORD coords="2260,2096,2327,2031">जी</WORD>
              <WORD coords="2351,2095,2405,2030">के</WORD>
              <WORD coords="2428,2098,2532,2049">ज्ञान</WORD>
              <WORD coords="2555,2095,2610,2030">के</WORD>
              <WORD coords="2634,2097,2798,2031">विस्तार</WORD>
              <WORD coords="2822,2097,2868,2031">से</WORD>
              <WORD coords="2893,2096,3083,2032">प्रभावित</WORD>
            </LINE>
            <LINE>
              <WORD coords="1704,2212,1750,2128">है</WORD>
              <WORD coords="1763,2197,1772,2147">।</WORD>
              <WORD coords="1806,2198,1918,2129">हरेक</WORD>
              <WORD coords="1948,2195,2084,2128">विषय</WORD>
              <WORD coords="2113,2197,2180,2148">पर</WORD>
              <WORD coords="2209,2198,2364,2129">उन्होंने</WORD>
              <WORD coords="2395,2197,2500,2129">हिदी</WORD>
              <WORD coords="2530,2195,2574,2128">में</WORD>
              <WORD coords="2603,2197,2738,2130">पाती</WORD>
              <WORD coords="2767,2198,2854,2147">बार</WORD>
              <WORD coords="2882,2196,3015,2129">लिखा</WORD>
              <WORD coords="3043,2198,3079,2126">है</WORD>
            </LINE>
            <LINE>
              <WORD coords="1706,2295,1803,2226">और</WORD>
              <WORD coords="1829,2294,1957,2228">उससे</WORD>
              <WORD coords="1985,2294,2114,2246">सजग</WORD>
              <WORD coords="2140,2293,2267,2229">किया</WORD>
              <WORD coords="2292,2296,2333,2225">है</WORD>
              <WORD coords="2360,2293,2520,2228">पाठकों</WORD>
              <WORD coords="2546,2294,2618,2228">को</WORD>
              <WORD coords="2638,2294,2646,2247">।</WORD>
              <WORD coords="2677,2295,2745,2245">पर</WORD>
              <WORD coords="2771,2294,2929,2228">जितना</WORD>
              <WORD coords="2954,2294,3085,2228">उनके&quot;</WORD>
            </LINE>
            <LINE>
              <WORD coords="1704,2394,1869,2327">विस्तार</WORD>
              <WORD coords="1897,2393,1946,2326">से</WORD>
              <WORD coords="1973,2409,2019,2325">हूँ</WORD>
              <WORD coords="2038,2392,2167,2328">उनके</WORD>
              <WORD coords="2193,2393,2303,2345">काम</WORD>
              <WORD coords="2331,2392,2385,2327">के</WORD>
              <WORD coords="2413,2394,2510,2345">स्तर</WORD>
              <WORD coords="2538,2394,2636,2324">और</WORD>
              <WORD coords="2663,2412,2847,2345">गुणवत्ता</WORD>
              <WORD coords="2875,2393,2921,2326">से</WORD>
              <WORD coords="2948,2393,3081,2344">उतना</WORD>
            </LINE>
            <LINE>
              <WORD coords="1705,2509,1844,2428">संतुष्ट</WORD>
              <WORD coords="1868,2492,1961,2425">नहीं</WORD>
              <WORD coords="1985,2508,2034,2424">हूँ</WORD>
              <WORD coords="2061,2490,2256,2425">प्रभावित</WORD>
              <WORD coords="2278,2492,2372,2425">नहीं</WORD>
              <WORD coords="2396,2493,2507,2425">होता</WORD>
              <WORD coords="2532,2507,2577,2424">हूँ</WORD>
              <WORD coords="2593,2489,2726,2425">बल्कि</WORD>
              <WORD coords="2749,2496,2833,2422">कई</WORD>
              <WORD coords="2857,2491,2942,2443">बार</WORD>
              <WORD coords="2965,2490,3083,2425">खीज</WORD>
            </LINE>
            <LINE>
              <WORD coords="1707,2589,1769,2524">भी</WORD>
              <WORD coords="1794,2590,1904,2523">होती</WORD>
              <WORD coords="1928,2591,1967,2520">है</WORD>
              <WORD coords="1992,2588,2064,2524">कि</WORD>
              <WORD coords="2087,2590,2241,2523">उन्होंने</WORD>
              <WORD coords="2267,2595,2397,2541">इतना</WORD>
              <WORD coords="2421,2589,2593,2523">पश्चिम</WORD>
              <WORD coords="2617,2590,2745,2524">करके</WORD>
              <WORD coords="2769,2588,2896,2522">किया</WORD>
              <WORD coords="2918,2590,2958,2520">है</WORD>
              <WORD coords="2983,2589,3076,2520">और</WORD>
            </LINE>
            <LINE>
              <WORD coords="1704,2693,1831,2622">इतनी</WORD>
              <WORD coords="1856,2704,2146,2621">सरलतापूर्वक</WORD>
              <WORD coords="2171,2686,2236,2622">जो</WORD>
              <WORD coords="2261,2686,2305,2622">ये</WORD>
              <WORD coords="2329,2686,2496,2620">निष्कर्ष</WORD>
              <WORD coords="2520,2686,2727,2621">निकालते</WORD>
              <WORD coords="2749,2690,2788,2618">हैं</WORD>
              <WORD coords="2808,2688,2816,2640">।</WORD>
              <WORD coords="2842,2687,2995,2620">जिदगी</WORD>
              <WORD coords="3018,2687,3080,2640">या</WORD>
            </LINE>
            <LINE>
              <WORD coords="1704,2786,1865,2720">विचारों</WORD>
              <WORD coords="1897,2784,1967,2720">क्री</WORD>
              <WORD coords="1999,2804,2149,2721">दुनिया</WORD>
              <WORD coords="2183,2791,2311,2720">इतनी</WORD>
              <WORD coords="2345,2795,2474,2737">साल,</WORD>
              <WORD coords="2511,2795,2648,2738">सहज,</WORD>
              <WORD coords="2683,2794,2774,2738">एक</WORD>
              <WORD coords="2805,2786,2956,2720">स्तरीय</WORD>
              <WORD coords="2987,2787,3080,2720">नहीं</WORD>
            </LINE>
            <LINE>
              <WORD coords="1704,2885,1813,2818">होती</WORD>
              <WORD coords="1843,2885,1883,2816">है</WORD>
              <WORD coords="1902,2884,1911,2837">।</WORD>
              <WORD coords="1946,2885,2046,2817">जहाँ</WORD>
              <WORD coords="2076,2883,2168,2836">तक</WORD>
              <WORD coords="2199,2885,2362,2836">नामवर</WORD>
              <WORD coords="2392,2884,2459,2820">जी</WORD>
              <WORD coords="2491,2884,2562,2836">का</WORD>
              <WORD coords="2592,2884,2737,2836">सवाल</WORD>
              <WORD coords="2767,2886,2807,2815">है</WORD>
              <WORD coords="2836,2883,2917,2816">मैंने</WORD>
              <WORD coords="2948,2883,3079,2817">केवल</WORD>
            </LINE>
            <LINE>
              <WORD coords="1706,2982,1936,2915">अंतर्विरोध</WORD>
              <WORD coords="1960,2981,2031,2916">को</WORD>
              <WORD coords="2056,2983,2216,2915">दिखाने</WORD>
              <WORD coords="2241,2982,2313,2917">की</WORD>
              <WORD coords="2337,2984,2518,2916">कोशिश</WORD>
              <WORD coords="2542,2981,2612,2916">कीं</WORD>
              <WORD coords="2641,2981,2702,2916">थी</WORD>
              <WORD coords="2723,2982,2732,2935">।</WORD>
              <WORD coords="2759,2981,2903,2916">उनकी</WORD>
              <WORD coords="2927,2999,3079,2933">पुस्तक</WORD>
            </LINE>
            <LINE>
              <WORD coords="1704,3077,1758,3012">के</WORD>
              <WORD coords="1786,3095,1893,3013">दूसरे</WORD>
              <WORD coords="1921,3078,2058,3031">तमाम</WORD>
              <WORD coords="2086,3078,2255,3012">निष्कर्ष</WORD>
              <WORD coords="2283,3097,2440,3014">मुझको</WORD>
              <WORD coords="2469,3096,2583,3031">वहुत</WORD>
              <WORD coords="2610,3095,2829,3011">महत्वपूर्ण</WORD>
              <WORD coords="2856,3078,2979,3012">लगते</WORD>
              <WORD coords="3006,3081,3047,3010">हैं</WORD>
              <WORD coords="3066,3079,3083,3032">।</WORD>
            </LINE>
            <LINE>
              <WORD coords="1704,3177,1864,3111">कविता</WORD>
              <WORD coords="1897,3176,1966,3113">की</WORD>
              <WORD coords="2001,3177,2229,3112">आलोचना</WORD>
              <WORD coords="2260,3178,2328,3130">पर</WORD>
              <WORD coords="2360,3184,2464,3111">ऐसी</WORD>
              <WORD coords="2496,3195,2649,3129">पुस्तक</WORD>
              <WORD coords="2681,3196,2794,3129">वहुत</WORD>
              <WORD coords="2825,3178,2917,3112">नहीं</WORD>
              <WORD coords="2947,3180,2987,3108">हैं</WORD>
              <WORD coords="3018,3176,3078,3111">तो</WORD>
            </LINE>
            <LINE>
              <WORD coords="1703,3280,1821,3208">इसमें</WORD>
              <WORD coords="1844,3281,1945,3208">कोई</WORD>
              <WORD coords="1974,3278,2067,3228">शक</WORD>
              <WORD coords="2090,3277,2183,3211">नहीं</WORD>
              <WORD coords="2205,3274,2213,3229">।</WORD>
              <WORD coords="2241,3276,2307,3228">पर</WORD>
              <WORD coords="2331,3275,2418,3209">मेरा</WORD>
              <WORD coords="2444,3276,2521,3227">यह</WORD>
              <WORD coords="2547,3293,2731,3227">अनुमान</WORD>
              <WORD coords="2757,3274,2817,3227">था</WORD>
              <WORD coords="2841,3275,2911,3210">कि</WORD>
              <WORD coords="2934,3274,3076,3209">उनकी</WORD>
            </LINE>
            <LINE>
              <WORD coords="1704,3373,1863,3307">रुचियों</WORD>
              <WORD coords="1893,3372,1936,3307">में</WORD>
              <WORD coords="1966,3382,2057,3326">एक</WORD>
              <WORD coords="2086,3375,2189,3325">तरह</WORD>
              <WORD coords="2218,3373,2289,3326">का</WORD>
              <WORD coords="2318,3374,2438,3326">उदार</WORD>
              <WORD coords="2468,3372,2675,3308">व्यक्तित्व</WORD>
              <WORD coords="2703,3376,2743,3305">है</WORD>
              <WORD coords="2761,3373,2770,3325">।</WORD>
              <WORD coords="2803,3372,2947,3307">उनको</WORD>
              <WORD coords="2976,3381,3077,3307">ऐसी</WORD>
            </LINE>
            <LINE>
              <WORD coords="1704,3489,1897,3406">वहुत-सी</WORD>
              <WORD coords="1925,3470,2035,3406">चीजे</WORD>
              <WORD coords="2064,3470,2200,3406">अच्छी</WORD>
              <WORD coords="2228,3470,2369,3405">लगती</WORD>
              <WORD coords="2397,3472,2436,3403">हैं</WORD>
              <WORD coords="2463,3470,2523,3406">तो</WORD>
              <WORD coords="2553,3470,2689,3406">अच्छी</WORD>
              <WORD coords="2717,3473,2755,3403">है</WORD>
              <WORD coords="2782,3470,2848,3405">जो</WORD>
              <WORD coords="2877,3470,3076,3404">आदोलन</WORD>
            </LINE>
            <LINE>
              <WORD coords="1704,3568,1756,3502">के</WORD>
              <WORD coords="1777,3569,1881,3503">लोग</WORD>
              <WORD coords="1903,3575,2040,3503">इनको</WORD>
              <WORD coords="2065,3570,2237,3503">नकारते</WORD>
              <WORD coords="2258,3571,2298,3501">हैं</WORD>
              <WORD coords="2318,3569,2326,3523">।</WORD>
              <WORD coords="2353,3570,2448,3500">कैसे</WORD>
              <WORD coords="2472,3569,2632,3504">आदमी</WORD>
              <WORD coords="2657,3569,2725,3504">की</WORD>
              <WORD coords="2748,3568,2905,3501">रुचियाँ</WORD>
              <WORD coords="2930,3568,3069,3506">अतत:</WORD>
            </LINE>
            <LINE>
              <WORD coords="1704,3666,1946,3600">अभी-कभी</WORD>
              <WORD coords="1973,3666,2033,3602">तो</WORD>
              <WORD coords="2060,3685,2175,3619">बहुत</WORD>
              <WORD coords="2201,3667,2364,3600">विरोधी</WORD>
              <WORD coords="2392,3668,2538,3601">स्थिति</WORD>
              <WORD coords="2563,3666,2607,3600">में</WORD>
              <WORD coords="2634,3666,2756,3618">प्रकट</WORD>
              <WORD coords="2784,3667,2892,3599">होती</WORD>
              <WORD coords="2919,3668,2958,3597">हैं</WORD>
              <WORD coords="2977,3667,2985,3620">।</WORD>
              <WORD coords="3017,3666,3076,3600">तो</WORD>
            </LINE>
            <LINE>
              <WORD coords="1703,3764,1784,3696">मैंने</WORD>
              <WORD coords="1808,3764,1930,3699">उसमें</WORD>
              <WORD coords="1953,3767,2046,3700">यही</WORD>
              <WORD coords="2071,3767,2196,3699">कहने</WORD>
              <WORD coords="2220,3763,2291,3699">की</WORD>
              <WORD coords="2315,3767,2495,3700">कोशिश</WORD>
              <WORD coords="2517,3764,2588,3700">की</WORD>
              <WORD coords="2611,3766,2651,3696">है</WORD>
              <WORD coords="2671,3764,2679,3717">।</WORD>
              <WORD coords="2708,3762,2750,3696">मैं</WORD>
              <WORD coords="2775,3766,2851,3716">यह</WORD>
              <WORD coords="2874,3766,2965,3699">नहीं</WORD>
              <WORD coords="2989,3766,3076,3717">का</WORD>
            </LINE>
            <LINE>
              <WORD coords="1703,3865,1785,3815">रहा</WORD>
              <WORD coords="1823,3880,1868,3797">हूँ</WORD>
              <WORD coords="1898,3862,1968,3798">कि</WORD>
              <WORD coords="2005,3864,2166,3816">नामवर</WORD>
              <WORD coords="2205,3865,2306,3797">सिंह</WORD>
              <WORD coords="2343,3863,2528,3798">रूपवादीं</WORD>
              <WORD coords="2570,3862,2790,3796">आलोचक</WORD>
              <WORD coords="2828,3865,2882,3798">हो</WORD>
              <WORD coords="2920,3871,3000,3814">गए</WORD>
              <WORD coords="3035,3864,3074,3794">हैं</WORD>
            </LINE>
            <LINE>
              <WORD coords="1705,3961,1838,3896">बल्कि</WORD>
              <WORD coords="1869,3961,1913,3894">मैं</WORD>
              <WORD coords="1945,3964,2023,3914">यह</WORD>
              <WORD coords="2054,3964,2141,3914">कह</WORD>
              <WORD coords="2173,3963,2256,3914">रहा</WORD>
              <WORD coords="2289,3979,2334,3895">हूँ</WORD>
              <WORD coords="2361,3961,2432,3896">की</WORD>
              <WORD coords="2466,3962,2593,3896">अपने</WORD>
              <WORD coords="2625,3963,2786,3895">विचारों</WORD>
              <WORD coords="2819,3960,2872,3896">के</WORD>
              <WORD coords="2905,3978,3075,3913">बावजूद</WORD>
            </LINE>
          </PARAGRAPH>
        </REGION>
      </PAGECOLUMN>
      <PAGECOLUMN>
        <REGION>
          <PARAGRAPH>
            <LINE>
              <WORD coords="2967,4151,2995,4103">२</WORD>
              <WORD coords="3004,4153,3027,4101">१</WORD>
              <WORD coords="3033,4150,3068,4102">९</WORD>
            </LINE>
          </PARAGRAPH>
        </REGION>
      </PAGECOLUMN>
    </HIDDENTEXT>
</OBJECT>
<MAP name="0219.djvu" >
</MAP>
</BODY>
</DjVuXML>
